[
  {
    "Rfc": "RFC",
    "VencimientoObligacion": "Vencimiento Obligacion",
    "FechayHoradeEmision": "Fecha y Hora de Emision",
    "VigenteHasta": "Vigente Hasta",
    "LineadeCaptura": "Linea de Captura",
    "ImporteTotalaPagar": "Importe Total a Pagar",
    "FechadelPago": "Fecha del Pago",
    "ImportePagado": "Importe Pagado",
    "NodeOperacion": "No de Operaci\u00F3n",
    "LlavedePago": "Llave de Pago",
    "Periodo": "Periodo",
    "Marca": "Marca",
    "FechadeConsulta": "Fecha de Consulta"
  },
  {
    "Rfc": "AABM940613SX1",
    "VencimientoObligacion": "",
    "FechayHoradeEmision": "",
    "VigenteHasta": "",
    "LineadeCaptura": "",
    "ImporteTotalaPagar": "",
    "FechadelPago": "",
    "ImportePagado": "",
    "NodeOperacion": "",
    "LlavedePago": "",
    "Periodo": "Agosto",
    "Marca": "No presentado",
    "FechadeConsulta": "22-09-2025"
  },
  {
    "Rfc": "AAZ1709049Z4",
    "VencimientoObligacion": "19/09/2025",
    "FechayHoradeEmision": "22/09/2025 - 10:14",
    "VigenteHasta": "22/09/2025",
    "LineadeCaptura": "0425 6G6J 2900 4733 5491",
    "ImporteTotalaPagar": "$33,168",
    "FechadelPago": "19/09/2025",
    "ImportePagado": "$33,168",
    "NodeOperacion": "122625123036",
    "LlavedePago": "AE1D847691",
    "Periodo": "Agosto",
    "Marca": "",
    "FechadeConsulta": "22-09-2025"
  },
  {
    "Rfc": "ABM1412236L5",
    "VencimientoObligacion": "19/09/2025",
    "FechayHoradeEmision": "22/09/2025 - 10:14",
    "VigenteHasta": "22/09/2025",
    "LineadeCaptura": "0425 6HNQ 1800 4733 0459",
    "ImporteTotalaPagar": "$319,940",
    "FechadelPago": "19/09/2025",
    "ImportePagado": "$319,940",
    "NodeOperacion": "522678926225",
    "LlavedePago": "331979B695",
    "Periodo": "Agosto",
    "Marca": "",
    "FechadeConsulta": "22-09-2025"
  },
  {
    "Rfc": "ACE991214JQ0",
    "VencimientoObligacion": "",
    "FechayHoradeEmision": "",
    "VigenteHasta": "",
    "LineadeCaptura": "",
    "ImporteTotalaPagar": "",
    "FechadelPago": "",
    "ImportePagado": "",
    "NodeOperacion": "",
    "LlavedePago": "",
    "Periodo": "Agosto",
    "Marca": "No presentado",
    "FechadeConsulta": "22-09-2025"
  },
  {
    "Rfc": "ALA9407148NA",
    "VencimientoObligacion": "19/09/2025",
    "FechayHoradeEmision": "22/09/2025 - 10:15",
    "VigenteHasta": "22/09/2025",
    "LineadeCaptura": "0425 65BT 6200 4733 3490",
    "ImporteTotalaPagar": "$20,681",
    "FechadelPago": "09/09/2025",
    "ImportePagado": "$20,681",
    "NodeOperacion": "122525430056",
    "LlavedePago": "860A5AF892",
    "Periodo": "Agosto",
    "Marca": "",
    "FechadeConsulta": "22-09-2025"
  },
  {
    "Rfc": "ARI081003GY8",
    "VencimientoObligacion": "19/09/2025",
    "FechayHoradeEmision": "22/09/2025 - 10:15",
    "VigenteHasta": "22/09/2025",
    "LineadeCaptura": "0425 69NW 6100 4733 1432",
    "ImporteTotalaPagar": "$81,635",
    "FechadelPago": "12/09/2025",
    "ImportePagado": "$81,635",
    "NodeOperacion": "11991789",
    "LlavedePago": "B955675191",
    "Periodo": "Agosto",
    "Marca": "",
    "FechadeConsulta": "22-09-2025"
  },
  {
    "Rfc": "BAU2111047L4",
    "VencimientoObligacion": "19/09/2025",
    "FechayHoradeEmision": "22/09/2025 - 10:15",
    "VigenteHasta": "22/09/2025",
    "LineadeCaptura": "0425 6GPN 6500 4733 0425",
    "ImporteTotalaPagar": "$48,352",
    "FechadelPago": "19/09/2025",
    "ImportePagado": "$48,352",
    "NodeOperacion": "122625065690",
    "LlavedePago": "F0B4860C96",
    "Periodo": "Agosto",
    "Marca": "",
    "FechadeConsulta": "22-09-2025"
  },
  {
    "Rfc": "BEMO830224IWA",
    "VencimientoObligacion": "19/09/2025",
    "FechayHoradeEmision": " 22/09/2025 - 10:1",
    "VigenteHasta": "22/09/2025",
    "LineadeCaptura": "0425 6I8O 4700 4733 4242",
    "ImporteTotalaPagar": "$143,196",
    "FechadelPago": "19/09/2025",
    "ImportePagado": "$143,196",
    "NodeOperacion": "9910445",
    "LlavedePago": "1F03FE4999",
    "Periodo": "Agosto",
    "Marca": "",
    "FechadeConsulta": "22-09-2025"
  },
  {
    "Rfc": "BTC1808244BA",
    "VencimientoObligacion": "",
    "FechayHoradeEmision": "",
    "VigenteHasta": "",
    "LineadeCaptura": "",
    "ImporteTotalaPagar": "",
    "FechadelPago": "",
    "ImportePagado": "",
    "NodeOperacion": "",
    "LlavedePago": "",
    "Periodo": "Agosto",
    "Marca": "No presentado",
    "FechadeConsulta": "22-09-2025"
  },
  {
    "Rfc": "CAMR440113MSA",
    "VencimientoObligacion": "19/09/2025",
    "FechayHoradeEmision": " 22/09/2025 - 10:1",
    "VigenteHasta": "22/09/2025",
    "LineadeCaptura": "0425 6G0V 8200 4733 8214",
    "ImporteTotalaPagar": "$57,529",
    "FechadelPago": "18/09/2025",
    "ImportePagado": "$57,529",
    "NodeOperacion": "122615039581",
    "LlavedePago": "209EAF9293",
    "Periodo": "Agosto",
    "Marca": "",
    "FechadeConsulta": "22-09-2025"
  },
  {
    "Rfc": "CAS120814MJ9",
    "VencimientoObligacion": "",
    "FechayHoradeEmision": "",
    "VigenteHasta": "",
    "LineadeCaptura": "",
    "ImporteTotalaPagar": "",
    "FechadelPago": "",
    "ImportePagado": "",
    "NodeOperacion": "",
    "LlavedePago": "",
    "Periodo": "Agosto",
    "Marca": "No presentado",
    "FechadeConsulta": "22-09-2025"
  },
  {
    "Rfc": "CBE2007238X7",
    "VencimientoObligacion": "19/09/2025",
    "FechayHoradeEmision": "22/09/2025 - 10:17",
    "VigenteHasta": "22/09/2025",
    "LineadeCaptura": "0425 6B72 7800 4733 1463",
    "ImporteTotalaPagar": "$30,523",
    "FechadelPago": "17/09/2025",
    "ImportePagado": "$30,523",
    "NodeOperacion": "9884579",
    "LlavedePago": "704C2EF291",
    "Periodo": "Agosto",
    "Marca": "",
    "FechadeConsulta": "22-09-2025"
  },
  {
    "Rfc": "CCH210604I83",
    "VencimientoObligacion": "",
    "FechayHoradeEmision": "",
    "VigenteHasta": "",
    "LineadeCaptura": "",
    "ImporteTotalaPagar": "",
    "FechadelPago": "",
    "ImportePagado": "",
    "NodeOperacion": "",
    "LlavedePago": "",
    "Periodo": "Agosto",
    "Marca": "No presentado",
    "FechadeConsulta": "22-09-2025"
  },
  {
    "Rfc": "CDE1711137C8",
    "VencimientoObligacion": "",
    "FechayHoradeEmision": "",
    "VigenteHasta": "",
    "LineadeCaptura": "",
    "ImporteTotalaPagar": "",
    "FechadelPago": "",
    "ImportePagado": "",
    "NodeOperacion": "",
    "LlavedePago": "",
    "Periodo": "Agosto",
    "Marca": "No presentado",
    "FechadeConsulta": "22-09-2025"
  },
  {
    "Rfc": "CFR120113PI0",
    "VencimientoObligacion": "",
    "FechayHoradeEmision": "",
    "VigenteHasta": "",
    "LineadeCaptura": "",
    "ImporteTotalaPagar": "",
    "FechadelPago": "",
    "ImportePagado": "",
    "NodeOperacion": "",
    "LlavedePago": "",
    "Periodo": "Agosto",
    "Marca": "No presentado",
    "FechadeConsulta": "22-09-2025"
  },
  {
    "Rfc": "CID230613466",
    "VencimientoObligacion": "19/09/2025",
    "FechayHoradeEmision": "22/09/2025 - 10:18",
    "VigenteHasta": "22/09/2025",
    "LineadeCaptura": "0425 67MA 4200 4733 8419",
    "ImporteTotalaPagar": "$75,437",
    "FechadelPago": "11/09/2025",
    "ImportePagado": "$75,437",
    "NodeOperacion": "122545594063",
    "LlavedePago": "2D372C3B98",
    "Periodo": "Agosto",
    "Marca": "",
    "FechadeConsulta": "22-09-2025"
  },
  {
    "Rfc": "CIN161123IX9",
    "VencimientoObligacion": "19/09/2025",
    "FechayHoradeEmision": "22/09/2025 - 10:18",
    "VigenteHasta": "22/09/2025",
    "LineadeCaptura": "0425 6I98 2900 4733 0491",
    "ImporteTotalaPagar": "$67,377",
    "FechadelPago": "19/09/2025",
    "ImportePagado": "$67,377",
    "NodeOperacion": "521808826225",
    "LlavedePago": "015E2CE493",
    "Periodo": "Agosto",
    "Marca": "",
    "FechadeConsulta": "22-09-2025"
  },
  {
    "Rfc": "CLF150504115",
    "VencimientoObligacion": "",
    "FechayHoradeEmision": "",
    "VigenteHasta": "",
    "LineadeCaptura": "",
    "ImporteTotalaPagar": "",
    "FechadelPago": "",
    "ImportePagado": "",
    "NodeOperacion": "",
    "LlavedePago": "",
    "Periodo": "Agosto",
    "Marca": "No presentado",
    "FechadeConsulta": "22-09-2025"
  },
  {
    "Rfc": "CON1303046Z0",
    "VencimientoObligacion": "19/09/2025",
    "FechayHoradeEmision": "22/09/2025 - 10:19",
    "VigenteHasta": "22/09/2025",
    "LineadeCaptura": "0425 6AJH 8300 4733 7414",
    "ImporteTotalaPagar": "$25,354",
    "FechadelPago": "18/09/2025",
    "ImportePagado": "$25,354",
    "NodeOperacion": "122615987130",
    "LlavedePago": "14503C9194",
    "Periodo": "Agosto",
    "Marca": "",
    "FechadeConsulta": "22-09-2025"
  },
  {
    "Rfc": "DCE190404A31",
    "VencimientoObligacion": "",
    "FechayHoradeEmision": "",
    "VigenteHasta": "",
    "LineadeCaptura": "",
    "ImporteTotalaPagar": "",
    "FechadelPago": "",
    "ImportePagado": "",
    "NodeOperacion": "",
    "LlavedePago": "",
    "Periodo": "Agosto",
    "Marca": "No presentado",
    "FechadeConsulta": "22-09-2025"
  },
  {
    "Rfc": "DCO110714JH9",
    "VencimientoObligacion": "19/09/2025",
    "FechayHoradeEmision": "22/09/2025 - 10:20",
    "VigenteHasta": "22/09/2025",
    "LineadeCaptura": "0425 6FSJ 6800 4733 2423",
    "ImporteTotalaPagar": "$30,333",
    "FechadelPago": "17/09/2025",
    "ImportePagado": "$30,333",
    "NodeOperacion": "513118826025",
    "LlavedePago": "2D65ACFC97",
    "Periodo": "Agosto",
    "Marca": "",
    "FechadeConsulta": "22-09-2025"
  },
  {
    "Rfc": "DEL890203G39",
    "VencimientoObligacion": "19/09/2025",
    "FechayHoradeEmision": "22/09/2025 - 10:20",
    "VigenteHasta": "22/09/2025",
    "LineadeCaptura": "0425 6IQN 9100 4733 8439",
    "ImporteTotalaPagar": "$49,140",
    "FechadelPago": "19/09/2025",
    "ImportePagado": "$49,140",
    "NodeOperacion": "520912126225",
    "LlavedePago": "A8FC55EF93",
    "Periodo": "Agosto",
    "Marca": "",
    "FechadeConsulta": "22-09-2025"
  },
  {
    "Rfc": "DEL890203G39",
    "VencimientoObligacion": "19/09/2025",
    "FechayHoradeEmision": "22/09/2025 - 10:20",
    "VigenteHasta": "22/09/2025",
    "LineadeCaptura": "0425 6FK2 5000 4733 6412",
    "ImporteTotalaPagar": "$15,769",
    "FechadelPago": "17/09/2025",
    "ImportePagado": "$15,769",
    "NodeOperacion": "513243026025",
    "LlavedePago": "AE852D7E99",
    "Periodo": "Agosto",
    "Marca": "",
    "FechadeConsulta": "22-09-2025"
  },
  {
    "Rfc": "DSN1611048Y9",
    "VencimientoObligacion": "19/09/2025",
    "FechayHoradeEmision": "22/09/2025 - 10:20",
    "VigenteHasta": "22/09/2025",
    "LineadeCaptura": "0425 6HGU 7300 4733 3418",
    "ImporteTotalaPagar": "$46,342",
    "FechadelPago": "19/09/2025",
    "ImportePagado": "$46,342",
    "NodeOperacion": "26708",
    "LlavedePago": "7F5599A299",
    "Periodo": "Agosto",
    "Marca": "",
    "FechadeConsulta": "22-09-2025"
  },
  {
    "Rfc": "DSN1611048Y9",
    "VencimientoObligacion": "19/09/2025",
    "FechayHoradeEmision": "22/09/2025 - 10:21",
    "VigenteHasta": "22/09/2025",
    "LineadeCaptura": "0425 6FLM 1900 4733 5448",
    "ImporteTotalaPagar": "$2,917",
    "FechadelPago": "19/09/2025",
    "ImportePagado": "$2,917",
    "NodeOperacion": "26468",
    "LlavedePago": "CE756D8991",
    "Periodo": "Agosto",
    "Marca": "",
    "FechadeConsulta": "22-09-2025"
  },
  {
    "Rfc": "EAB970203FV5",
    "VencimientoObligacion": "19/09/2025",
    "FechayHoradeEmision": "22/09/2025 - 10:21",
    "VigenteHasta": "22/09/2025",
    "LineadeCaptura": "0425 68TW 8900 4733 8490",
    "ImporteTotalaPagar": "$289,870",
    "FechadelPago": "11/09/2025",
    "ImportePagado": "$289,870",
    "NodeOperacion": "50522198",
    "LlavedePago": "F2CADF6390",
    "Periodo": "Agosto",
    "Marca": "",
    "FechadeConsulta": "22-09-2025"
  },
  {
    "Rfc": "ECA220623VB9",
    "VencimientoObligacion": "",
    "FechayHoradeEmision": "",
    "VigenteHasta": "",
    "LineadeCaptura": "",
    "ImporteTotalaPagar": "",
    "FechadelPago": "",
    "ImportePagado": "",
    "NodeOperacion": "",
    "LlavedePago": "",
    "Periodo": "Agosto",
    "Marca": "No presentado",
    "FechadeConsulta": "22-09-2025"
  },
  {
    "Rfc": "EDC220224IQ8",
    "VencimientoObligacion": "19/09/2025",
    "FechayHoradeEmision": "22/09/2025 - 10:21",
    "VigenteHasta": "22/09/2025",
    "LineadeCaptura": "0425 6H0B 2900 4733 5494",
    "ImporteTotalaPagar": "$125,300",
    "FechadelPago": "18/09/2025",
    "ImportePagado": "$125,300",
    "NodeOperacion": "122615023020",
    "LlavedePago": "6AA22A2297",
    "Periodo": "Agosto",
    "Marca": "",
    "FechadeConsulta": "22-09-2025"
  },
  {
    "Rfc": "EVA1505048I9",
    "VencimientoObligacion": "19/09/2025",
    "FechayHoradeEmision": "22/09/2025 - 10:22",
    "VigenteHasta": "22/09/2025",
    "LineadeCaptura": "0425 6IHT 3500 4733 9434",
    "ImporteTotalaPagar": "$84,324",
    "FechadelPago": "19/09/2025",
    "ImportePagado": "$84,324",
    "NodeOperacion": "521620626225",
    "LlavedePago": "02D56F4994",
    "Periodo": "Agosto",
    "Marca": "",
    "FechadeConsulta": "22-09-2025"
  },
  {
    "Rfc": "FAT2003241I5",
    "VencimientoObligacion": "19/09/2025",
    "FechayHoradeEmision": "22/09/2025 - 10:22",
    "VigenteHasta": "22/09/2025",
    "LineadeCaptura": "0425 6J9C 4700 4733 6419",
    "ImporteTotalaPagar": "$58,919",
    "FechadelPago": "19/09/2025",
    "ImportePagado": "$58,919",
    "NodeOperacion": "522496726225",
    "LlavedePago": "8B32A77992",
    "Periodo": "Agosto",
    "Marca": "",
    "FechadeConsulta": "22-09-2025"
  },
  {
    "Rfc": "FRE220503SP7",
    "VencimientoObligacion": "19/09/2025",
    "FechayHoradeEmision": "22/09/2025 - 10:23",
    "VigenteHasta": "22/09/2025",
    "LineadeCaptura": "0425 6GVO 6200 4733 9444",
    "ImporteTotalaPagar": "$7,431",
    "FechadelPago": "18/09/2025",
    "ImportePagado": "$7,431",
    "NodeOperacion": "9898435",
    "LlavedePago": "D865C57E95",
    "Periodo": "Agosto",
    "Marca": "",
    "FechadeConsulta": "22-09-2025"
  },
  {
    "Rfc": "FRU100603JA6",
    "VencimientoObligacion": "19/09/2025",
    "FechayHoradeEmision": "22/09/2025 - 10:23",
    "VigenteHasta": "22/09/2025",
    "LineadeCaptura": "0425 6FUQ 9100 4733 0455",
    "ImporteTotalaPagar": "$58,892",
    "FechadelPago": "19/09/2025",
    "ImportePagado": "$58,892",
    "NodeOperacion": "122625129012",
    "LlavedePago": "93AC6D0895",
    "Periodo": "Agosto",
    "Marca": "",
    "FechadeConsulta": "22-09-2025"
  },
  {
    "Rfc": "FWI210614C32",
    "VencimientoObligacion": "19/09/2025",
    "FechayHoradeEmision": "22/09/2025 - 10:23",
    "VigenteHasta": "22/09/2025",
    "LineadeCaptura": "0425 6EZT 7600 4733 0457",
    "ImporteTotalaPagar": "$93,017",
    "FechadelPago": "18/09/2025",
    "ImportePagado": "$93,017",
    "NodeOperacion": "50634221",
    "LlavedePago": "D9AA9B4798",
    "Periodo": "Agosto",
    "Marca": "",
    "FechadeConsulta": "22-09-2025"
  },
  {
    "Rfc": "GER041124HM3",
    "VencimientoObligacion": "19/09/2025",
    "FechayHoradeEmision": "22/09/2025 - 10:24",
    "VigenteHasta": "22/09/2025",
    "LineadeCaptura": "0425 6BJU 4800 4733 3430",
    "ImporteTotalaPagar": "$19,487",
    "FechadelPago": "15/09/2025",
    "ImportePagado": "$19,487",
    "NodeOperacion": "11997284",
    "LlavedePago": "B5078B8A94",
    "Periodo": "Agosto",
    "Marca": "",
    "FechadeConsulta": "22-09-2025"
  },
  {
    "Rfc": "GFM2206141DA",
    "VencimientoObligacion": "19/09/2025",
    "FechayHoradeEmision": "22/09/2025 - 10:24",
    "VigenteHasta": "22/09/2025",
    "LineadeCaptura": "0425 696L 2900 4733 1488",
    "ImporteTotalaPagar": "$51,728",
    "FechadelPago": "11/09/2025",
    "ImportePagado": "$51,728",
    "NodeOperacion": "298908",
    "LlavedePago": "E0B0E66C91",
    "Periodo": "Agosto",
    "Marca": "",
    "FechadeConsulta": "22-09-2025"
  },
  {
    "Rfc": "GOAI8612042P1",
    "VencimientoObligacion": "19/09/2025",
    "FechayHoradeEmision": " 22/09/2025 - 10:2",
    "VigenteHasta": "22/09/2025",
    "LineadeCaptura": "0425 69DB 2700 4733 0280",
    "ImporteTotalaPagar": "$12,559",
    "FechadelPago": "17/09/2025",
    "ImportePagado": "$12,559",
    "NodeOperacion": "12006512",
    "LlavedePago": "6251C6F199",
    "Periodo": "Agosto",
    "Marca": "",
    "FechadeConsulta": "22-09-2025"
  },
  {
    "Rfc": "HPE200723BM6",
    "VencimientoObligacion": "",
    "FechayHoradeEmision": "",
    "VigenteHasta": "",
    "LineadeCaptura": "",
    "ImporteTotalaPagar": "",
    "FechadelPago": "",
    "ImportePagado": "",
    "NodeOperacion": "",
    "LlavedePago": "",
    "Periodo": "Agosto",
    "Marca": "No presentado",
    "FechadeConsulta": "22-09-2025"
  },
  {
    "Rfc": "IEC160504LG8",
    "VencimientoObligacion": "19/09/2025",
    "FechayHoradeEmision": "22/09/2025 - 10:25",
    "VigenteHasta": "22/09/2025",
    "LineadeCaptura": "0425 6ANY 5800 4733 5474",
    "ImporteTotalaPagar": "$280,148",
    "FechadelPago": "15/09/2025",
    "ImportePagado": "$280,148",
    "NodeOperacion": "9869811",
    "LlavedePago": "DAA9662295",
    "Periodo": "Agosto",
    "Marca": "",
    "FechadeConsulta": "22-09-2025"
  },
  {
    "Rfc": "IIM180213K77",
    "VencimientoObligacion": "",
    "FechayHoradeEmision": "",
    "VigenteHasta": "",
    "LineadeCaptura": "",
    "ImporteTotalaPagar": "",
    "FechadelPago": "",
    "ImportePagado": "",
    "NodeOperacion": "",
    "LlavedePago": "",
    "Periodo": "Agosto",
    "Marca": "No presentado",
    "FechadeConsulta": "22-09-2025"
  },
  {
    "Rfc": "IOCL760804HU2",
    "VencimientoObligacion": "",
    "FechayHoradeEmision": "",
    "VigenteHasta": "",
    "LineadeCaptura": "",
    "ImporteTotalaPagar": "",
    "FechadelPago": "",
    "ImportePagado": "",
    "NodeOperacion": "",
    "LlavedePago": "",
    "Periodo": "Agosto",
    "Marca": "No presentado",
    "FechadeConsulta": "22-09-2025"
  },
  {
    "Rfc": "LOMI671223181",
    "VencimientoObligacion": "",
    "FechayHoradeEmision": "",
    "VigenteHasta": "",
    "LineadeCaptura": "",
    "ImporteTotalaPagar": "",
    "FechadelPago": "",
    "ImportePagado": "",
    "NodeOperacion": "",
    "LlavedePago": "",
    "Periodo": "Agosto",
    "Marca": "No presentado",
    "FechadeConsulta": "22-09-2025"
  },
  {
    "Rfc": "LPL170124I73",
    "VencimientoObligacion": "",
    "FechayHoradeEmision": "",
    "VigenteHasta": "",
    "LineadeCaptura": "",
    "ImporteTotalaPagar": "",
    "FechadelPago": "",
    "ImportePagado": "",
    "NodeOperacion": "",
    "LlavedePago": "",
    "Periodo": "Agosto",
    "Marca": "No presentado",
    "FechadeConsulta": "22-09-2025"
  },
  {
    "Rfc": "MAFJ721224790",
    "VencimientoObligacion": "",
    "FechayHoradeEmision": "",
    "VigenteHasta": "",
    "LineadeCaptura": "",
    "ImporteTotalaPagar": "",
    "FechadelPago": "",
    "ImportePagado": "",
    "NodeOperacion": "",
    "LlavedePago": "",
    "Periodo": "Agosto",
    "Marca": "No presentado",
    "FechadeConsulta": "22-09-2025"
  },
  {
    "Rfc": "MDE1512033R4",
    "VencimientoObligacion": "",
    "FechayHoradeEmision": "",
    "VigenteHasta": "",
    "LineadeCaptura": "",
    "ImporteTotalaPagar": "",
    "FechadelPago": "",
    "ImportePagado": "",
    "NodeOperacion": "",
    "LlavedePago": "",
    "Periodo": "Agosto",
    "Marca": "No presentado",
    "FechadeConsulta": "22-09-2025"
  },
  {
    "Rfc": "MECM671014G17",
    "VencimientoObligacion": "19/09/2025",
    "FechayHoradeEmision": " 22/09/2025 - 10:2",
    "VigenteHasta": "22/09/2025",
    "LineadeCaptura": "0425 6DVZ 0700 4733 5277",
    "ImporteTotalaPagar": "$146,516",
    "FechadelPago": "17/09/2025",
    "ImportePagado": "$146,516",
    "NodeOperacion": "50595156",
    "LlavedePago": "C9A3604195",
    "Periodo": "Agosto",
    "Marca": "",
    "FechadeConsulta": "22-09-2025"
  },
  {
    "Rfc": "MMA140723QF6",
    "VencimientoObligacion": "",
    "FechayHoradeEmision": "",
    "VigenteHasta": "",
    "LineadeCaptura": "",
    "ImporteTotalaPagar": "",
    "FechadelPago": "",
    "ImportePagado": "",
    "NodeOperacion": "",
    "LlavedePago": "",
    "Periodo": "Agosto",
    "Marca": "No presentado",
    "FechadeConsulta": "22-09-2025"
  },
  {
    "Rfc": "MUN041203HS8",
    "VencimientoObligacion": "19/09/2025",
    "FechayHoradeEmision": "22/09/2025 - 10:28",
    "VigenteHasta": "22/09/2025",
    "LineadeCaptura": "0425 6ARQ 8100 4733 0446",
    "ImporteTotalaPagar": "$72,975",
    "FechadelPago": "15/09/2025",
    "ImportePagado": "$72,975",
    "NodeOperacion": "130768",
    "LlavedePago": "AFA21AF492",
    "Periodo": "Agosto",
    "Marca": "",
    "FechadeConsulta": "22-09-2025"
  },
  {
    "Rfc": "NADR630104GP3",
    "VencimientoObligacion": "",
    "FechayHoradeEmision": "",
    "VigenteHasta": "",
    "LineadeCaptura": "",
    "ImporteTotalaPagar": "",
    "FechadelPago": "",
    "ImportePagado": "",
    "NodeOperacion": "",
    "LlavedePago": "",
    "Periodo": "Agosto",
    "Marca": "No presentado",
    "FechadeConsulta": "22-09-2025"
  },
  {
    "Rfc": "NCA131204PV0",
    "VencimientoObligacion": "19/09/2025",
    "FechayHoradeEmision": "22/09/2025 - 10:28",
    "VigenteHasta": "22/09/2025",
    "LineadeCaptura": "0425 6D7V 2000 4733 7411",
    "ImporteTotalaPagar": "$87,347",
    "FechadelPago": "17/09/2025",
    "ImportePagado": "$87,347",
    "NodeOperacion": "122605899401",
    "LlavedePago": "9A4E2B8199",
    "Periodo": "Agosto",
    "Marca": "",
    "FechadeConsulta": "22-09-2025"
  },
  {
    "Rfc": "NSI221013P3A",
    "VencimientoObligacion": "19/09/2025",
    "FechayHoradeEmision": "22/09/2025 - 10:29",
    "VigenteHasta": "22/09/2025",
    "LineadeCaptura": "0425 6H5I 5200 4733 2470",
    "ImporteTotalaPagar": "$22,017",
    "FechadelPago": "18/09/2025",
    "ImportePagado": "$22,017",
    "NodeOperacion": "5398491",
    "LlavedePago": "D320386797",
    "Periodo": "Agosto",
    "Marca": "",
    "FechadeConsulta": "22-09-2025"
  },
  {
    "Rfc": "OAM1607133Q8",
    "VencimientoObligacion": "19/09/2025",
    "FechayHoradeEmision": "22/09/2025 - 10:29",
    "VigenteHasta": "22/09/2025",
    "LineadeCaptura": "0425 6GO1 9900 4733 4445",
    "ImporteTotalaPagar": "$95,965",
    "FechadelPago": "19/09/2025",
    "ImportePagado": "$95,965",
    "NodeOperacion": "522059626225",
    "LlavedePago": "26D3E30F95",
    "Periodo": "Agosto",
    "Marca": "",
    "FechadeConsulta": "22-09-2025"
  },
  {
    "Rfc": "OCA020524BZ9",
    "VencimientoObligacion": "",
    "FechayHoradeEmision": "",
    "VigenteHasta": "",
    "LineadeCaptura": "",
    "ImporteTotalaPagar": "",
    "FechadelPago": "",
    "ImportePagado": "",
    "NodeOperacion": "",
    "LlavedePago": "",
    "Periodo": "Agosto",
    "Marca": "No presentado",
    "FechadeConsulta": "22-09-2025"
  },
  {
    "Rfc": "OCC2401242J7",
    "VencimientoObligacion": "19/09/2025",
    "FechayHoradeEmision": "22/09/2025 - 10:30",
    "VigenteHasta": "22/09/2025",
    "LineadeCaptura": "0425 6HNN 7600 4733 5462",
    "ImporteTotalaPagar": "$113,549",
    "FechadelPago": "19/09/2025",
    "ImportePagado": "$113,549",
    "NodeOperacion": "122625052994",
    "LlavedePago": "3C30F9DA97",
    "Periodo": "Agosto",
    "Marca": "",
    "FechadeConsulta": "22-09-2025"
  },
  {
    "Rfc": "OHB221004RC0",
    "VencimientoObligacion": "19/09/2025",
    "FechayHoradeEmision": "22/09/2025 - 10:30",
    "VigenteHasta": "22/09/2025",
    "LineadeCaptura": "0425 6G4N 6700 4733 8442",
    "ImporteTotalaPagar": "$297,301",
    "FechadelPago": "18/09/2025",
    "ImportePagado": "$297,301",
    "NodeOperacion": "122615015035",
    "LlavedePago": "4A363E3699",
    "Periodo": "Agosto",
    "Marca": "",
    "FechadeConsulta": "22-09-2025"
  },
  {
    "Rfc": "OLV0506137J1",
    "VencimientoObligacion": "",
    "FechayHoradeEmision": "",
    "VigenteHasta": "",
    "LineadeCaptura": "",
    "ImporteTotalaPagar": "",
    "FechadelPago": "",
    "ImportePagado": "",
    "NodeOperacion": "",
    "LlavedePago": "",
    "Periodo": "Agosto",
    "Marca": "No presentado",
    "FechadeConsulta": "22-09-2025"
  },
  {
    "Rfc": "OTC180703731",
    "VencimientoObligacion": "19/09/2025",
    "FechayHoradeEmision": "22/09/2025 - 10:31",
    "VigenteHasta": "22/09/2025",
    "LineadeCaptura": "0425 6FPJ 2900 4733 3418",
    "ImporteTotalaPagar": "$32,453",
    "FechadelPago": "17/09/2025",
    "ImportePagado": "$32,453",
    "NodeOperacion": "12006913",
    "LlavedePago": "19BBE8A491",
    "Periodo": "Agosto",
    "Marca": "",
    "FechadeConsulta": "22-09-2025"
  },
  {
    "Rfc": "PCA210803AI0",
    "VencimientoObligacion": "",
    "FechayHoradeEmision": "",
    "VigenteHasta": "",
    "LineadeCaptura": "",
    "ImporteTotalaPagar": "",
    "FechadelPago": "",
    "ImportePagado": "",
    "NodeOperacion": "",
    "LlavedePago": "",
    "Periodo": "Agosto",
    "Marca": "No presentado",
    "FechadeConsulta": "22-09-2025"
  },
  {
    "Rfc": "PCG170804S59",
    "VencimientoObligacion": "19/09/2025",
    "FechayHoradeEmision": "22/09/2025 - 10:32",
    "VigenteHasta": "22/09/2025",
    "LineadeCaptura": "0425 6F06 2600 4733 4459",
    "ImporteTotalaPagar": "$64,640",
    "FechadelPago": "17/09/2025",
    "ImportePagado": "$64,640",
    "NodeOperacion": "5387486",
    "LlavedePago": "A5F7B57192",
    "Periodo": "Agosto",
    "Marca": "",
    "FechadeConsulta": "22-09-2025"
  },
  {
    "Rfc": "PMA190214G28",
    "VencimientoObligacion": "",
    "FechayHoradeEmision": "",
    "VigenteHasta": "",
    "LineadeCaptura": "",
    "ImporteTotalaPagar": "",
    "FechadelPago": "",
    "ImportePagado": "",
    "NodeOperacion": "",
    "LlavedePago": "",
    "Periodo": "Agosto",
    "Marca": "No presentado",
    "FechadeConsulta": "22-09-2025"
  },
  {
    "Rfc": "ROMA790423V39",
    "VencimientoObligacion": "19/09/2025",
    "FechayHoradeEmision": " 22/09/2025 - 10:3",
    "VigenteHasta": "22/09/2025",
    "LineadeCaptura": "0425 6EH9 3200 4733 0285",
    "ImporteTotalaPagar": "$44,624",
    "FechadelPago": "17/09/2025",
    "ImportePagado": "$44,624",
    "NodeOperacion": "3590544683",
    "LlavedePago": "34575AE094",
    "Periodo": "Agosto",
    "Marca": "",
    "FechadeConsulta": "22-09-2025"
  },
  {
    "Rfc": "RSR170213NM5",
    "VencimientoObligacion": "",
    "FechayHoradeEmision": "",
    "VigenteHasta": "",
    "LineadeCaptura": "",
    "ImporteTotalaPagar": "",
    "FechadelPago": "",
    "ImportePagado": "",
    "NodeOperacion": "",
    "LlavedePago": "",
    "Periodo": "Agosto",
    "Marca": "No presentado",
    "FechadeConsulta": "22-09-2025"
  },
  {
    "Rfc": "SAT1404035Y7",
    "VencimientoObligacion": "",
    "FechayHoradeEmision": "",
    "VigenteHasta": "",
    "LineadeCaptura": "",
    "ImporteTotalaPagar": "",
    "FechadelPago": "",
    "ImportePagado": "",
    "NodeOperacion": "",
    "LlavedePago": "",
    "Periodo": "Agosto",
    "Marca": "No presentado",
    "FechadeConsulta": "22-09-2025"
  },
  {
    "Rfc": "SCE150223LA9",
    "VencimientoObligacion": "19/09/2025",
    "FechayHoradeEmision": "22/09/2025 - 10:35",
    "VigenteHasta": "22/09/2025",
    "LineadeCaptura": "0425 66O2 4500 4733 8410",
    "ImporteTotalaPagar": "$71,129",
    "FechadelPago": "09/09/2025",
    "ImportePagado": "$71,129",
    "NodeOperacion": "50504027",
    "LlavedePago": "F08B129196",
    "Periodo": "Agosto",
    "Marca": "",
    "FechadeConsulta": "22-09-2025"
  },
  {
    "Rfc": "SDV170724RR8",
    "VencimientoObligacion": "19/09/2025",
    "FechayHoradeEmision": "22/09/2025 - 10:35",
    "VigenteHasta": "22/09/2025",
    "LineadeCaptura": "0425 6IW7 3600 4733 0413",
    "ImporteTotalaPagar": "$31,433",
    "FechadelPago": "19/09/2025",
    "ImportePagado": "$31,433",
    "NodeOperacion": "122625107736",
    "LlavedePago": "F0A51AA697",
    "Periodo": "Agosto",
    "Marca": "",
    "FechadeConsulta": "22-09-2025"
  },
  {
    "Rfc": "SNM210304RN4",
    "VencimientoObligacion": "19/09/2025",
    "FechayHoradeEmision": "22/09/2025 - 10:35",
    "VigenteHasta": "22/09/2025",
    "LineadeCaptura": "0425 6ESX 8000 4733 0451",
    "ImporteTotalaPagar": "$56,764",
    "FechadelPago": "17/09/2025",
    "ImportePagado": "$56,764",
    "NodeOperacion": "122605893002",
    "LlavedePago": "E202CE1691",
    "Periodo": "Agosto",
    "Marca": "",
    "FechadeConsulta": "22-09-2025"
  },
  {
    "Rfc": "STS050223AR8",
    "VencimientoObligacion": "",
    "FechayHoradeEmision": "",
    "VigenteHasta": "",
    "LineadeCaptura": "",
    "ImporteTotalaPagar": "",
    "FechadelPago": "",
    "ImportePagado": "",
    "NodeOperacion": "",
    "LlavedePago": "",
    "Periodo": "Agosto",
    "Marca": "No presentado",
    "FechadeConsulta": "22-09-2025"
  },
  {
    "Rfc": "TSM1707038X4",
    "VencimientoObligacion": "",
    "FechayHoradeEmision": "",
    "VigenteHasta": "",
    "LineadeCaptura": "",
    "ImporteTotalaPagar": "",
    "FechadelPago": "",
    "ImportePagado": "",
    "NodeOperacion": "",
    "LlavedePago": "",
    "Periodo": "Agosto",
    "Marca": "No presentado",
    "FechadeConsulta": "22-09-2025"
  },
  {
    "Rfc": "TUR1303046A6",
    "VencimientoObligacion": "19/09/2025",
    "FechayHoradeEmision": "22/09/2025 - 10:36",
    "VigenteHasta": "22/09/2025",
    "LineadeCaptura": "0425 6AIQ 3300 4733 5402",
    "ImporteTotalaPagar": "$53,104",
    "FechadelPago": "19/09/2025",
    "ImportePagado": "$53,104",
    "NodeOperacion": "9906329",
    "LlavedePago": "2AB8A2F990",
    "Periodo": "Agosto",
    "Marca": "",
    "FechadeConsulta": "22-09-2025"
  },
  {
    "Rfc": "UAE141204718",
    "VencimientoObligacion": "19/09/2025",
    "FechayHoradeEmision": "22/09/2025 - 10:36",
    "VigenteHasta": "22/09/2025",
    "LineadeCaptura": "0425 6FBR 7800 4733 3459",
    "ImporteTotalaPagar": "$114,489",
    "FechadelPago": "18/09/2025",
    "ImportePagado": "$114,489",
    "NodeOperacion": "9889542",
    "LlavedePago": "F56411D091",
    "Periodo": "Agosto",
    "Marca": "",
    "FechadeConsulta": "22-09-2025"
  },
  {
    "Rfc": "UNE19051315A",
    "VencimientoObligacion": "19/09/2025",
    "FechayHoradeEmision": "22/09/2025 - 10:37",
    "VigenteHasta": "22/09/2025",
    "LineadeCaptura": "0425 6FRO 1700 4733 6445",
    "ImporteTotalaPagar": "$47,726",
    "FechadelPago": "19/09/2025",
    "ImportePagado": "$47,726",
    "NodeOperacion": "122625057614",
    "LlavedePago": "C9501A9795",
    "Periodo": "Agosto",
    "Marca": "",
    "FechadeConsulta": "22-09-2025"
  },
  {
    "Rfc": "VPA191104HPA",
    "VencimientoObligacion": "",
    "FechayHoradeEmision": "",
    "VigenteHasta": "",
    "LineadeCaptura": "",
    "ImporteTotalaPagar": "",
    "FechadelPago": "",
    "ImportePagado": "",
    "NodeOperacion": "",
    "LlavedePago": "",
    "Periodo": "Agosto",
    "Marca": "No presentado",
    "FechadeConsulta": "22-09-2025"
  },
  {
    "Rfc": "YVA210713UK2",
    "VencimientoObligacion": "19/09/2025",
    "FechayHoradeEmision": "22/09/2025 - 10:37",
    "VigenteHasta": "22/09/2025",
    "LineadeCaptura": "0425 69ZH 5300 4733 3440",
    "ImporteTotalaPagar": "$136,854",
    "FechadelPago": "17/09/2025",
    "ImportePagado": "$136,854",
    "NodeOperacion": "508933826025",
    "LlavedePago": "7AE1353C94",
    "Periodo": "Agosto",
    "Marca": "",
    "FechadeConsulta": "22-09-2025"
  },
  {
    "Rfc": "ZSO091014I97",
    "VencimientoObligacion": "",
    "FechayHoradeEmision": "",
    "VigenteHasta": "",
    "LineadeCaptura": "",
    "ImporteTotalaPagar": "",
    "FechadelPago": "",
    "ImportePagado": "",
    "NodeOperacion": "",
    "LlavedePago": "",
    "Periodo": "Agosto",
    "Marca": "No presentado",
    "FechadeConsulta": "22-09-2025"
  },
  {
    "Rfc": "PTI120614GLA",
    "VencimientoObligacion": "19/09/2025",
    "FechayHoradeEmision": "22/09/2025 - 10:32",
    "VigenteHasta": "22/09/2025",
    "LineadeCaptura": "0425 6J8A 5500 4733 8494",
    "ImporteTotalaPagar": "$69,250",
    "FechadelPago": "19/09/2025",
    "ImportePagado": "$69,250",
    "NodeOperacion": "50661094",
    "LlavedePago": "70ED385295",
    "Periodo": "Agosto",
    "Marca": "",
    "FechadeConsulta": "22-09-2025"
  }
]