[
  {
    "Rfc": "RFC",
    "VencimientoObligacion": "Vencimiento Obligacion",
    "FechayHoradeEmision": "Fecha y Hora de Emision",
    "VigenteHasta": "Vigente Hasta",
    "LineadeCaptura": "Linea de Captura",
    "ImporteTotalaPagar": "Importe Total a Pagar",
    "FechadelPago": "Fecha del Pago",
    "ImportePagado": "Importe Pagado",
    "NodeOperacion": "No de Operaci\u00F3n",
    "LlavedePago": "Llave de Pago",
    "Periodo": "Periodo",
    "Marca": "Marca",
    "FechadeConsulta": "Fecha de Consulta"
  },
  {
    "Rfc": "AACR4512097D7",
    "VencimientoObligacion": "",
    "FechayHoradeEmision": "",
    "VigenteHasta": "",
    "LineadeCaptura": "",
    "ImporteTotalaPagar": "",
    "FechadelPago": "",
    "ImportePagado": "",
    "NodeOperacion": "",
    "LlavedePago": "",
    "Periodo": "Julio",
    "Marca": "No presentado",
    "FechadeConsulta": "26-08-2025"
  },
  {
    "Rfc": "AAM070620PP3",
    "VencimientoObligacion": "25/08/2025",
    "FechayHoradeEmision": "26/08/2025 - 10:25",
    "VigenteHasta": "25/08/2025",
    "LineadeCaptura": "0425 5GXQ 7700 4705 8456",
    "ImporteTotalaPagar": "$46,154",
    "FechadelPago": "18/08/2025",
    "ImportePagado": "$46,154",
    "NodeOperacion": "96028",
    "LlavedePago": "C1C39FCF82",
    "Periodo": "Julio",
    "Marca": "",
    "FechadeConsulta": "26-08-2025"
  },
  {
    "Rfc": "ADA050209L21",
    "VencimientoObligacion": "25/08/2025",
    "FechayHoradeEmision": "26/08/2025 - 10:25",
    "VigenteHasta": "25/08/2025",
    "LineadeCaptura": "0425 5VJT 4900 4705 2442",
    "ImporteTotalaPagar": "$95,721",
    "FechadelPago": "25/08/2025",
    "ImportePagado": "$95,721",
    "NodeOperacion": "107356",
    "LlavedePago": "CC05EC3387",
    "Periodo": "Julio",
    "Marca": "",
    "FechadeConsulta": "26-08-2025"
  },
  {
    "Rfc": "APO1512091X8",
    "VencimientoObligacion": "",
    "FechayHoradeEmision": "",
    "VigenteHasta": "",
    "LineadeCaptura": "",
    "ImporteTotalaPagar": "",
    "FechadelPago": "",
    "ImportePagado": "",
    "NodeOperacion": "",
    "LlavedePago": "",
    "Periodo": "Julio",
    "Marca": "No presentado",
    "FechadeConsulta": "26-08-2025"
  },
  {
    "Rfc": "ARE2103303K9",
    "VencimientoObligacion": "25/08/2025",
    "FechayHoradeEmision": "26/08/2025 - 10:26",
    "VigenteHasta": "25/08/2025",
    "LineadeCaptura": "0425 5MMA 0600 4705 0406",
    "ImporteTotalaPagar": "$96,702",
    "FechadelPago": "20/08/2025",
    "ImportePagado": "$96,702",
    "NodeOperacion": "527250839377",
    "LlavedePago": "E4AD7A9884",
    "Periodo": "Julio",
    "Marca": "",
    "FechadeConsulta": "26-08-2025"
  },
  {
    "Rfc": "AUQF410529PK1",
    "VencimientoObligacion": "25/08/2025",
    "FechayHoradeEmision": " 26/08/2025 - 10:2",
    "VigenteHasta": "25/08/2025",
    "LineadeCaptura": "0425 5W6M 6200 4705 3298",
    "ImporteTotalaPagar": "$39,155",
    "FechadelPago": "25/08/2025",
    "ImportePagado": "$39,155",
    "NodeOperacion": "122375801722",
    "LlavedePago": "6CDDA76280",
    "Periodo": "Julio",
    "Marca": "",
    "FechadeConsulta": "26-08-2025"
  },
  {
    "Rfc": "BCA1307095F0",
    "VencimientoObligacion": "25/08/2025",
    "FechayHoradeEmision": "26/08/2025 - 10:26",
    "VigenteHasta": "25/08/2025",
    "LineadeCaptura": "0425 5K3J 2500 4705 9482",
    "ImporteTotalaPagar": "$50,820",
    "FechadelPago": "18/08/2025",
    "ImportePagado": "$50,820",
    "NodeOperacion": "9760042",
    "LlavedePago": "937707D686",
    "Periodo": "Julio",
    "Marca": "",
    "FechadeConsulta": "26-08-2025"
  },
  {
    "Rfc": "BCO191009CP3",
    "VencimientoObligacion": "25/08/2025",
    "FechayHoradeEmision": "26/08/2025 - 10:27",
    "VigenteHasta": "25/08/2025",
    "LineadeCaptura": "0425 5NO9 5000 4705 2410",
    "ImporteTotalaPagar": "$37,176",
    "FechadelPago": "17/08/2025",
    "ImportePagado": "$37,176",
    "NodeOperacion": "122295176178",
    "LlavedePago": "1E05907986",
    "Periodo": "Julio",
    "Marca": "",
    "FechadeConsulta": "26-08-2025"
  },
  {
    "Rfc": "BMS181220H35",
    "VencimientoObligacion": "25/08/2025",
    "FechayHoradeEmision": "26/08/2025 - 10:27",
    "VigenteHasta": "25/08/2025",
    "LineadeCaptura": "0425 5LQC 3300 4705 9441",
    "ImporteTotalaPagar": "$20,979",
    "FechadelPago": "15/08/2025",
    "ImportePagado": "$20,979",
    "NodeOperacion": "2816399",
    "LlavedePago": "B60E4EC681",
    "Periodo": "Julio",
    "Marca": "",
    "FechadeConsulta": "26-08-2025"
  },
  {
    "Rfc": "BOBL8601191H1",
    "VencimientoObligacion": "25/08/2025",
    "FechayHoradeEmision": " 26/08/2025 - 10:2",
    "VigenteHasta": "25/08/2025",
    "LineadeCaptura": "0425 5RAF 4300 4705 6220",
    "ImporteTotalaPagar": "$78,955",
    "FechadelPago": "25/08/2025",
    "ImportePagado": "$78,955",
    "NodeOperacion": "122375798404",
    "LlavedePago": "DFB2A1C486",
    "Periodo": "Julio",
    "Marca": "",
    "FechadeConsulta": "26-08-2025"
  },
  {
    "Rfc": "BSG030530FJA",
    "VencimientoObligacion": "25/08/2025",
    "FechayHoradeEmision": "26/08/2025 - 10:27",
    "VigenteHasta": "25/08/2025",
    "LineadeCaptura": "0425 5O8T 0900 4705 2401",
    "ImporteTotalaPagar": "$59,165",
    "FechadelPago": "19/08/2025",
    "ImportePagado": "$59,165",
    "NodeOperacion": "9768890",
    "LlavedePago": "7CD86B9081",
    "Periodo": "Julio",
    "Marca": "",
    "FechadeConsulta": "26-08-2025"
  },
  {
    "Rfc": "CACD751119FP0",
    "VencimientoObligacion": "25/08/2025",
    "FechayHoradeEmision": " 26/08/2025 - 10:2",
    "VigenteHasta": "25/08/2025",
    "LineadeCaptura": "0425 5VMN 5700 4705 9254",
    "ImporteTotalaPagar": "$79,801",
    "FechadelPago": "25/08/2025",
    "ImportePagado": "$79,801",
    "NodeOperacion": "581025723725",
    "LlavedePago": "5EC357DE80",
    "Periodo": "Julio",
    "Marca": "",
    "FechadeConsulta": "26-08-2025"
  },
  {
    "Rfc": "CAF130930HI4",
    "VencimientoObligacion": "25/08/2025",
    "FechayHoradeEmision": "26/08/2025 - 10:28",
    "VigenteHasta": "25/08/2025",
    "LineadeCaptura": "0425 5X2W 7100 4705 6400",
    "ImporteTotalaPagar": "$45,052",
    "FechadelPago": "25/08/2025",
    "ImportePagado": "$45,052",
    "NodeOperacion": "122375892376",
    "LlavedePago": "B913AAB880",
    "Periodo": "Julio",
    "Marca": "",
    "FechadeConsulta": "26-08-2025"
  },
  {
    "Rfc": "CAGJ620929LP8",
    "VencimientoObligacion": "25/08/2025",
    "FechayHoradeEmision": " 26/08/2025 - 10:2",
    "VigenteHasta": "25/08/2025",
    "LineadeCaptura": "0425 5WEN 4800 4705 2209",
    "ImporteTotalaPagar": "$18,225",
    "FechadelPago": "25/08/2025",
    "ImportePagado": "$18,225",
    "NodeOperacion": "579404023725",
    "LlavedePago": "196806C480",
    "Periodo": "Julio",
    "Marca": "",
    "FechadeConsulta": "26-08-2025"
  },
  {
    "Rfc": "CBC210810HA7",
    "VencimientoObligacion": "",
    "FechayHoradeEmision": "",
    "VigenteHasta": "",
    "LineadeCaptura": "",
    "ImporteTotalaPagar": "",
    "FechadelPago": "",
    "ImportePagado": "",
    "NodeOperacion": "",
    "LlavedePago": "",
    "Periodo": "Julio",
    "Marca": "No presentado",
    "FechadeConsulta": "26-08-2025"
  },
  {
    "Rfc": "CCA9307091U6",
    "VencimientoObligacion": "25/08/2025",
    "FechayHoradeEmision": "26/08/2025 - 10:29",
    "VigenteHasta": "25/08/2025",
    "LineadeCaptura": "0425 5Q3H 6400 4705 5498",
    "ImporteTotalaPagar": "$49,408",
    "FechadelPago": "22/08/2025",
    "ImportePagado": "$49,408",
    "NodeOperacion": "576728223425",
    "LlavedePago": "A6FDCA9389",
    "Periodo": "Julio",
    "Marca": "",
    "FechadeConsulta": "26-08-2025"
  },
  {
    "Rfc": "CCR150119FE4",
    "VencimientoObligacion": "",
    "FechayHoradeEmision": "",
    "VigenteHasta": "",
    "LineadeCaptura": "",
    "ImporteTotalaPagar": "",
    "FechadelPago": "",
    "ImportePagado": "",
    "NodeOperacion": "",
    "LlavedePago": "",
    "Periodo": "Julio",
    "Marca": "No presentado",
    "FechadeConsulta": "26-08-2025"
  },
  {
    "Rfc": "CEE120629MX6",
    "VencimientoObligacion": "25/08/2025",
    "FechayHoradeEmision": "26/08/2025 - 10:29",
    "VigenteHasta": "25/08/2025",
    "LineadeCaptura": "0425 5JDE 5400 4705 6409",
    "ImporteTotalaPagar": "$121,103",
    "FechadelPago": "18/08/2025",
    "ImportePagado": "$121,103",
    "NodeOperacion": "122305219102",
    "LlavedePago": "57DEE7B484",
    "Periodo": "Julio",
    "Marca": "",
    "FechadeConsulta": "26-08-2025"
  },
  {
    "Rfc": "CFL0611308V2",
    "VencimientoObligacion": "25/08/2025",
    "FechayHoradeEmision": "26/08/2025 - 10:30",
    "VigenteHasta": "25/08/2025",
    "LineadeCaptura": "0425 5UB1 3700 4705 8400",
    "ImporteTotalaPagar": "$44,941",
    "FechadelPago": "21/08/2025",
    "ImportePagado": "$44,941",
    "NodeOperacion": "574480023325",
    "LlavedePago": "463BB3F482",
    "Periodo": "Julio",
    "Marca": "",
    "FechadeConsulta": "26-08-2025"
  },
  {
    "Rfc": "CIA0203199C7",
    "VencimientoObligacion": "25/08/2025",
    "FechayHoradeEmision": "26/08/2025 - 10:30",
    "VigenteHasta": "25/08/2025",
    "LineadeCaptura": "0425 5MDG 2100 4705 2475",
    "ImporteTotalaPagar": "$20,183",
    "FechadelPago": "15/08/2025",
    "ImportePagado": "$20,183",
    "NodeOperacion": "554880322725",
    "LlavedePago": "209D815289",
    "Periodo": "Julio",
    "Marca": "",
    "FechadeConsulta": "26-08-2025"
  },
  {
    "Rfc": "CPU210319IC2",
    "VencimientoObligacion": "25/08/2025",
    "FechayHoradeEmision": "26/08/2025 - 10:30",
    "VigenteHasta": "25/08/2025",
    "LineadeCaptura": "0425 5WPT 5100 4705 5470",
    "ImporteTotalaPagar": "$88,964",
    "FechadelPago": "25/08/2025",
    "ImportePagado": "$88,964",
    "NodeOperacion": "122375839522",
    "LlavedePago": "D0B5E53489",
    "Periodo": "Julio",
    "Marca": "",
    "FechadeConsulta": "26-08-2025"
  },
  {
    "Rfc": "CVE1902198V3",
    "VencimientoObligacion": "25/08/2025",
    "FechayHoradeEmision": "26/08/2025 - 10:31",
    "VigenteHasta": "25/08/2025",
    "LineadeCaptura": "0425 5P29 2800 4705 1465",
    "ImporteTotalaPagar": "$19,425",
    "FechadelPago": "21/08/2025",
    "ImportePagado": "$19,425",
    "NodeOperacion": "50338997",
    "LlavedePago": "17E4CB2882",
    "Periodo": "Julio",
    "Marca": "",
    "FechadeConsulta": "26-08-2025"
  },
  {
    "Rfc": "DEVL890609LY6",
    "VencimientoObligacion": "25/08/2025",
    "FechayHoradeEmision": " 26/08/2025 - 10:3",
    "VigenteHasta": "25/08/2025",
    "LineadeCaptura": "0425 5KKV 0400 4705 9229",
    "ImporteTotalaPagar": "$63,077",
    "FechadelPago": "25/08/2025",
    "ImportePagado": "$63,077",
    "NodeOperacion": "3558858539",
    "LlavedePago": "F5BE1B4488",
    "Periodo": "Julio",
    "Marca": "",
    "FechadeConsulta": "26-08-2025"
  },
  {
    "Rfc": "DIE190409V84",
    "VencimientoObligacion": "25/08/2025",
    "FechayHoradeEmision": "26/08/2025 - 10:31",
    "VigenteHasta": "25/08/2025",
    "LineadeCaptura": "0425 5IXV 4400 4705 9474",
    "ImporteTotalaPagar": "$23,987",
    "FechadelPago": "12/08/2025",
    "ImportePagado": "$23,987",
    "NodeOperacion": "548897522425",
    "LlavedePago": "A4ADA91983",
    "Periodo": "Julio",
    "Marca": "",
    "FechadeConsulta": "26-08-2025"
  },
  {
    "Rfc": "DSI1312198Y8",
    "VencimientoObligacion": "",
    "FechayHoradeEmision": "",
    "VigenteHasta": "",
    "LineadeCaptura": "",
    "ImporteTotalaPagar": "",
    "FechadelPago": "",
    "ImportePagado": "",
    "NodeOperacion": "",
    "LlavedePago": "",
    "Periodo": "Julio",
    "Marca": "No presentado",
    "FechadeConsulta": "26-08-2025"
  },
  {
    "Rfc": "EIBA700919F70",
    "VencimientoObligacion": "25/08/2025",
    "FechayHoradeEmision": " 26/08/2025 - 10:3",
    "VigenteHasta": "25/08/2025",
    "LineadeCaptura": "0425 5SQR 2900 4705 1237",
    "ImporteTotalaPagar": "$14,873",
    "FechadelPago": "20/08/2025",
    "ImportePagado": "$14,873",
    "NodeOperacion": "570303823225",
    "LlavedePago": "4922E16D81",
    "Periodo": "Julio",
    "Marca": "",
    "FechadeConsulta": "26-08-2025"
  },
  {
    "Rfc": "EIRP791110PY9",
    "VencimientoObligacion": "",
    "FechayHoradeEmision": "",
    "VigenteHasta": "",
    "LineadeCaptura": "",
    "ImporteTotalaPagar": "",
    "FechadelPago": "",
    "ImportePagado": "",
    "NodeOperacion": "",
    "LlavedePago": "",
    "Periodo": "Julio",
    "Marca": "No presentado",
    "FechadeConsulta": "26-08-2025"
  },
  {
    "Rfc": "EKA221130RK0",
    "VencimientoObligacion": "",
    "FechayHoradeEmision": "",
    "VigenteHasta": "",
    "LineadeCaptura": "",
    "ImporteTotalaPagar": "",
    "FechadelPago": "",
    "ImportePagado": "",
    "NodeOperacion": "",
    "LlavedePago": "",
    "Periodo": "Julio",
    "Marca": "No presentado",
    "FechadeConsulta": "26-08-2025"
  },
  {
    "Rfc": "EMM1311207Q1",
    "VencimientoObligacion": "25/08/2025",
    "FechayHoradeEmision": "26/08/2025 - 10:32",
    "VigenteHasta": "25/08/2025",
    "LineadeCaptura": "0425 5V80 1800 4705 8493",
    "ImporteTotalaPagar": "$31,794",
    "FechadelPago": "25/08/2025",
    "ImportePagado": "$31,794",
    "NodeOperacion": "579532223725",
    "LlavedePago": "C274F1F289",
    "Periodo": "Julio",
    "Marca": "",
    "FechadeConsulta": "26-08-2025"
  },
  {
    "Rfc": "ESF150729565",
    "VencimientoObligacion": "25/08/2025",
    "FechayHoradeEmision": "26/08/2025 - 10:33",
    "VigenteHasta": "25/08/2025",
    "LineadeCaptura": "0425 5SR7 0000 4705 1499",
    "ImporteTotalaPagar": "$15,076",
    "FechadelPago": "21/08/2025",
    "ImportePagado": "$15,076",
    "NodeOperacion": "122335667639",
    "LlavedePago": "7249AF5F82",
    "Periodo": "Julio",
    "Marca": "",
    "FechadeConsulta": "26-08-2025"
  },
  {
    "Rfc": "ETA180830A5A",
    "VencimientoObligacion": "",
    "FechayHoradeEmision": "",
    "VigenteHasta": "",
    "LineadeCaptura": "",
    "ImporteTotalaPagar": "",
    "FechadelPago": "",
    "ImportePagado": "",
    "NodeOperacion": "",
    "LlavedePago": "",
    "Periodo": "Julio",
    "Marca": "No presentado",
    "FechadeConsulta": "26-08-2025"
  },
  {
    "Rfc": "FCA1610204E5",
    "VencimientoObligacion": "25/08/2025",
    "FechayHoradeEmision": "26/08/2025 - 10:33",
    "VigenteHasta": "25/08/2025",
    "LineadeCaptura": "0425 5W8X 1600 4705 1472",
    "ImporteTotalaPagar": "$116,243",
    "FechadelPago": "25/08/2025",
    "ImportePagado": "$116,243",
    "NodeOperacion": "122375844832",
    "LlavedePago": "EDD30E8784",
    "Periodo": "Julio",
    "Marca": "",
    "FechadeConsulta": "26-08-2025"
  },
  {
    "Rfc": "GAC150709F38",
    "VencimientoObligacion": "25/08/2025",
    "FechayHoradeEmision": "26/08/2025 - 10:33",
    "VigenteHasta": "25/08/2025",
    "LineadeCaptura": "0425 5OIS 4500 4705 7443",
    "ImporteTotalaPagar": "$29,479",
    "FechadelPago": "21/08/2025",
    "ImportePagado": "$29,479",
    "NodeOperacion": "50344863",
    "LlavedePago": "DF8817D084",
    "Periodo": "Julio",
    "Marca": "",
    "FechadeConsulta": "26-08-2025"
  },
  {
    "Rfc": "GAH200610RL6",
    "VencimientoObligacion": "25/08/2025",
    "FechayHoradeEmision": "26/08/2025 - 10:34",
    "VigenteHasta": "25/08/2025",
    "LineadeCaptura": "0425 5WGS 6700 4705 8448",
    "ImporteTotalaPagar": "$61,645",
    "FechadelPago": "25/08/2025",
    "ImportePagado": "$61,645",
    "NodeOperacion": "3559525260",
    "LlavedePago": "609BF98382",
    "Periodo": "Julio",
    "Marca": "",
    "FechadeConsulta": "26-08-2025"
  },
  {
    "Rfc": "GAL200820SY6",
    "VencimientoObligacion": "25/08/2025",
    "FechayHoradeEmision": "26/08/2025 - 10:34",
    "VigenteHasta": "25/08/2025",
    "LineadeCaptura": "0425 5HDM 6900 4705 1498",
    "ImporteTotalaPagar": "$36,442",
    "FechadelPago": "22/08/2025",
    "ImportePagado": "$36,442",
    "NodeOperacion": "9799607",
    "LlavedePago": "E35CD01589",
    "Periodo": "Julio",
    "Marca": "",
    "FechadeConsulta": "26-08-2025"
  },
  {
    "Rfc": "GAQ150320AB6",
    "VencimientoObligacion": "25/08/2025",
    "FechayHoradeEmision": "26/08/2025 - 10:34",
    "VigenteHasta": "25/08/2025",
    "LineadeCaptura": "0425 5HI0 7100 4705 3479",
    "ImporteTotalaPagar": "$20,670",
    "FechadelPago": "11/08/2025",
    "ImportePagado": "$20,670",
    "NodeOperacion": "50153702",
    "LlavedePago": "0AFE309D82",
    "Periodo": "Julio",
    "Marca": "",
    "FechadeConsulta": "26-08-2025"
  },
  {
    "Rfc": "GCB200519FX5",
    "VencimientoObligacion": "25/08/2025",
    "FechayHoradeEmision": "26/08/2025 - 10:35",
    "VigenteHasta": "25/08/2025",
    "LineadeCaptura": "0425 5PIS 0300 4705 2411",
    "ImporteTotalaPagar": "$11,727",
    "FechadelPago": "18/08/2025",
    "ImportePagado": "$11,727",
    "NodeOperacion": "122305264726",
    "LlavedePago": "630A1C3180",
    "Periodo": "Julio",
    "Marca": "",
    "FechadeConsulta": "26-08-2025"
  },
  {
    "Rfc": "GRE100120E51",
    "VencimientoObligacion": "25/08/2025",
    "FechayHoradeEmision": "26/08/2025 - 10:35",
    "VigenteHasta": "25/08/2025",
    "LineadeCaptura": "0425 5PI3 5200 4705 3494",
    "ImporteTotalaPagar": "$40,605",
    "FechadelPago": "20/08/2025",
    "ImportePagado": "$40,605",
    "NodeOperacion": "569142223225",
    "LlavedePago": "A92A438185",
    "Periodo": "Julio",
    "Marca": "",
    "FechadeConsulta": "26-08-2025"
  },
  {
    "Rfc": "HHI191219359",
    "VencimientoObligacion": "25/08/2025",
    "FechayHoradeEmision": "26/08/2025 - 10:35",
    "VigenteHasta": "25/08/2025",
    "LineadeCaptura": "0425 5WC1 3400 4705 3481",
    "ImporteTotalaPagar": "$15,038",
    "FechadelPago": "25/08/2025",
    "ImportePagado": "$15,038",
    "NodeOperacion": "122375797201",
    "LlavedePago": "C96B7D1084",
    "Periodo": "Julio",
    "Marca": "",
    "FechadeConsulta": "26-08-2025"
  },
  {
    "Rfc": "HSA990820GV3",
    "VencimientoObligacion": "25/08/2025",
    "FechayHoradeEmision": "26/08/2025 - 10:36",
    "VigenteHasta": "25/08/2025",
    "LineadeCaptura": "0425 5V7D 3000 4705 6493",
    "ImporteTotalaPagar": "$35,385",
    "FechadelPago": "22/08/2025",
    "ImportePagado": "$35,385",
    "NodeOperacion": "9803914",
    "LlavedePago": "506542A781",
    "Periodo": "Julio",
    "Marca": "",
    "FechadeConsulta": "26-08-2025"
  },
  {
    "Rfc": "IMA0605098W0",
    "VencimientoObligacion": "",
    "FechayHoradeEmision": "",
    "VigenteHasta": "",
    "LineadeCaptura": "",
    "ImporteTotalaPagar": "",
    "FechadelPago": "",
    "ImportePagado": "",
    "NodeOperacion": "",
    "LlavedePago": "",
    "Periodo": "Julio",
    "Marca": "No presentado",
    "FechadeConsulta": "26-08-2025"
  },
  {
    "Rfc": "LEMG800619S77",
    "VencimientoObligacion": "25/08/2025",
    "FechayHoradeEmision": " 26/08/2025 - 10:3",
    "VigenteHasta": "25/08/2025",
    "LineadeCaptura": "0425 5V55 7600 4705 2270",
    "ImporteTotalaPagar": "$18,203",
    "FechadelPago": "22/08/2025",
    "ImportePagado": "$18,203",
    "NodeOperacion": "122345715000",
    "LlavedePago": "8C925A4980",
    "Periodo": "Julio",
    "Marca": "",
    "FechadeConsulta": "26-08-2025"
  },
  {
    "Rfc": "LTI100630SQ8",
    "VencimientoObligacion": "25/08/2025",
    "FechayHoradeEmision": "26/08/2025 - 10:36",
    "VigenteHasta": "25/08/2025",
    "LineadeCaptura": "0425 5U0B 5000 4705 1445",
    "ImporteTotalaPagar": "$11,230",
    "FechadelPago": "25/08/2025",
    "ImportePagado": "$11,230",
    "NodeOperacion": "9808796",
    "LlavedePago": "2BE08A8F81",
    "Periodo": "Julio",
    "Marca": "",
    "FechadeConsulta": "26-08-2025"
  },
  {
    "Rfc": "MAB170110AE1",
    "VencimientoObligacion": "25/08/2025",
    "FechayHoradeEmision": "26/08/2025 - 10:37",
    "VigenteHasta": "25/08/2025",
    "LineadeCaptura": "0425 5MO8 8000 4705 5435",
    "ImporteTotalaPagar": "$25,949",
    "FechadelPago": "15/08/2025",
    "ImportePagado": "$25,949",
    "NodeOperacion": "50201408",
    "LlavedePago": "9F617F2482",
    "Periodo": "Julio",
    "Marca": "",
    "FechadeConsulta": "26-08-2025"
  },
  {
    "Rfc": "MAGF671010PK7",
    "VencimientoObligacion": "25/08/2025",
    "FechayHoradeEmision": " 26/08/2025 - 10:3",
    "VigenteHasta": "25/08/2025",
    "LineadeCaptura": "0425 5H15 4200 4705 3253",
    "ImporteTotalaPagar": "$51,445",
    "FechadelPago": "25/08/2025",
    "ImportePagado": "$51,445",
    "NodeOperacion": "579330223725",
    "LlavedePago": "07F5A53188",
    "Periodo": "Julio",
    "Marca": "",
    "FechadeConsulta": "26-08-2025"
  },
  {
    "Rfc": "MAMT460510N40",
    "VencimientoObligacion": "25/08/2025",
    "FechayHoradeEmision": " 26/08/2025 - 10:3",
    "VigenteHasta": "25/08/2025",
    "LineadeCaptura": "0425 5O1U 0000 4705 7205",
    "ImporteTotalaPagar": "$68,678",
    "FechadelPago": "19/08/2025",
    "ImportePagado": "$68,678",
    "NodeOperacion": "73405",
    "LlavedePago": "B265988B89",
    "Periodo": "Julio",
    "Marca": "",
    "FechadeConsulta": "26-08-2025"
  },
  {
    "Rfc": "MAN9801092M9",
    "VencimientoObligacion": "25/08/2025",
    "FechayHoradeEmision": "26/08/2025 - 10:38",
    "VigenteHasta": "25/08/2025",
    "LineadeCaptura": "0425 5ICY 2000 4705 9408",
    "ImporteTotalaPagar": "$20,861",
    "FechadelPago": "12/08/2025",
    "ImportePagado": "$20,861",
    "NodeOperacion": "9735696",
    "LlavedePago": "ED7FCD6B86",
    "Periodo": "Julio",
    "Marca": "",
    "FechadeConsulta": "26-08-2025"
  },
  {
    "Rfc": "MAP180710UI0",
    "VencimientoObligacion": "25/08/2025",
    "FechayHoradeEmision": "26/08/2025 - 10:38",
    "VigenteHasta": "25/08/2025",
    "LineadeCaptura": "0425 5GUP 9400 4705 0439",
    "ImporteTotalaPagar": "$16,287",
    "FechadelPago": "15/08/2025",
    "ImportePagado": "$16,287",
    "NodeOperacion": "105435",
    "LlavedePago": "1539AE5781",
    "Periodo": "Julio",
    "Marca": "",
    "FechadeConsulta": "26-08-2025"
  },
  {
    "Rfc": "MDV220520N45",
    "VencimientoObligacion": "25/08/2025",
    "FechayHoradeEmision": "26/08/2025 - 10:38",
    "VigenteHasta": "25/08/2025",
    "LineadeCaptura": "0425 5NLX 6900 4705 5490",
    "ImporteTotalaPagar": "$132,605",
    "FechadelPago": "18/08/2025",
    "ImportePagado": "$132,605",
    "NodeOperacion": "507240425350",
    "LlavedePago": "AA7107EC86",
    "Periodo": "Julio",
    "Marca": "",
    "FechadeConsulta": "26-08-2025"
  },
  {
    "Rfc": "MUML560110341",
    "VencimientoObligacion": "25/08/2025",
    "FechayHoradeEmision": " 26/08/2025 - 10:3",
    "VigenteHasta": "25/08/2025",
    "LineadeCaptura": "0425 5BO7 4100 4705 6222",
    "ImporteTotalaPagar": "$58,599",
    "FechadelPago": "05/08/2025",
    "ImportePagado": "$58,599",
    "NodeOperacion": "122175588176",
    "LlavedePago": "406782E787",
    "Periodo": "Julio",
    "Marca": "",
    "FechadeConsulta": "26-08-2025"
  },
  {
    "Rfc": "NALK790729GA3",
    "VencimientoObligacion": "",
    "FechayHoradeEmision": "",
    "VigenteHasta": "",
    "LineadeCaptura": "",
    "ImporteTotalaPagar": "",
    "FechadelPago": "",
    "ImportePagado": "",
    "NodeOperacion": "",
    "LlavedePago": "",
    "Periodo": "Julio",
    "Marca": "No presentado",
    "FechadeConsulta": "26-08-2025"
  },
  {
    "Rfc": "NHE230309BJ3",
    "VencimientoObligacion": "25/08/2025",
    "FechayHoradeEmision": "26/08/2025 - 10:39",
    "VigenteHasta": "25/08/2025",
    "LineadeCaptura": "0425 5O80 1100 4705 2405",
    "ImporteTotalaPagar": "$172,826",
    "FechadelPago": "23/08/2025",
    "ImportePagado": "$172,826",
    "NodeOperacion": "122355780063",
    "LlavedePago": "1DFD7C1882",
    "Periodo": "Julio",
    "Marca": "",
    "FechadeConsulta": "26-08-2025"
  },
  {
    "Rfc": "NHO071130NB6",
    "VencimientoObligacion": "25/08/2025",
    "FechayHoradeEmision": "26/08/2025 - 10:39",
    "VigenteHasta": "25/08/2025",
    "LineadeCaptura": "0425 5R83 3300 4705 3474",
    "ImporteTotalaPagar": "$50,930",
    "FechadelPago": "19/08/2025",
    "ImportePagado": "$50,930",
    "NodeOperacion": "122315441731",
    "LlavedePago": "BEC1CE2381",
    "Periodo": "Julio",
    "Marca": "",
    "FechadeConsulta": "26-08-2025"
  },
  {
    "Rfc": "OHC180709S13",
    "VencimientoObligacion": "",
    "FechayHoradeEmision": "",
    "VigenteHasta": "",
    "LineadeCaptura": "",
    "ImporteTotalaPagar": "",
    "FechadelPago": "",
    "ImportePagado": "",
    "NodeOperacion": "",
    "LlavedePago": "",
    "Periodo": "Julio",
    "Marca": "No presentado",
    "FechadeConsulta": "26-08-2025"
  },
  {
    "Rfc": "PAN170830K26",
    "VencimientoObligacion": "25/08/2025",
    "FechayHoradeEmision": "26/08/2025 - 10:40",
    "VigenteHasta": "25/08/2025",
    "LineadeCaptura": "0425 5P13 1700 4705 0459",
    "ImporteTotalaPagar": "$60,824",
    "FechadelPago": "18/08/2025",
    "ImportePagado": "$60,824",
    "NodeOperacion": "50232458",
    "LlavedePago": "6AA11C1A89",
    "Periodo": "Julio",
    "Marca": "",
    "FechadeConsulta": "26-08-2025"
  },
  {
    "Rfc": "PIA190820371",
    "VencimientoObligacion": "",
    "FechayHoradeEmision": "",
    "VigenteHasta": "",
    "LineadeCaptura": "",
    "ImporteTotalaPagar": "",
    "FechadelPago": "",
    "ImportePagado": "",
    "NodeOperacion": "",
    "LlavedePago": "",
    "Periodo": "Julio",
    "Marca": "No presentado",
    "FechadeConsulta": "26-08-2025"
  },
  {
    "Rfc": "PJA130110FY4",
    "VencimientoObligacion": "25/08/2025",
    "FechayHoradeEmision": "26/08/2025 - 10:40",
    "VigenteHasta": "25/08/2025",
    "LineadeCaptura": "0425 5PSS 5200 4705 3422",
    "ImporteTotalaPagar": "$21,301",
    "FechadelPago": "18/08/2025",
    "ImportePagado": "$21,301",
    "NodeOperacion": "560422923025",
    "LlavedePago": "85B1D01E87",
    "Periodo": "Julio",
    "Marca": "",
    "FechadeConsulta": "26-08-2025"
  },
  {
    "Rfc": "PLE1608095RA",
    "VencimientoObligacion": "",
    "FechayHoradeEmision": "",
    "VigenteHasta": "",
    "LineadeCaptura": "",
    "ImporteTotalaPagar": "",
    "FechadelPago": "",
    "ImportePagado": "",
    "NodeOperacion": "",
    "LlavedePago": "",
    "Periodo": "Julio",
    "Marca": "No presentado",
    "FechadeConsulta": "26-08-2025"
  },
  {
    "Rfc": "PPC240119460",
    "VencimientoObligacion": "25/08/2025",
    "FechayHoradeEmision": "26/08/2025 - 10:41",
    "VigenteHasta": "25/08/2025",
    "LineadeCaptura": "0425 5O4U 2400 4705 3495",
    "ImporteTotalaPagar": "$76,334",
    "FechadelPago": "20/08/2025",
    "ImportePagado": "$76,334",
    "NodeOperacion": "122325496999",
    "LlavedePago": "B351454D81",
    "Periodo": "Julio",
    "Marca": "",
    "FechadeConsulta": "26-08-2025"
  },
  {
    "Rfc": "PPC240119460",
    "VencimientoObligacion": "25/08/2025",
    "FechayHoradeEmision": "26/08/2025 - 10:41",
    "VigenteHasta": "25/08/2025",
    "LineadeCaptura": "0425 5BTL 4900 4705 7449",
    "ImporteTotalaPagar": "$5,288",
    "FechadelPago": "08/08/2025",
    "ImportePagado": "$5,288",
    "NodeOperacion": "122205783932",
    "LlavedePago": "ECB460A384",
    "Periodo": "Julio",
    "Marca": "",
    "FechadeConsulta": "26-08-2025"
  },
  {
    "Rfc": "RERJ680320HJ0",
    "VencimientoObligacion": "",
    "FechayHoradeEmision": "",
    "VigenteHasta": "",
    "LineadeCaptura": "",
    "ImporteTotalaPagar": "",
    "FechadelPago": "",
    "ImportePagado": "",
    "NodeOperacion": "",
    "LlavedePago": "",
    "Periodo": "Julio",
    "Marca": "No presentado",
    "FechadeConsulta": "26-08-2025"
  },
  {
    "Rfc": "SAE220509TJ2",
    "VencimientoObligacion": "25/08/2025",
    "FechayHoradeEmision": "26/08/2025 - 10:41",
    "VigenteHasta": "25/08/2025",
    "LineadeCaptura": "0425 5R9C 2300 4705 3482",
    "ImporteTotalaPagar": "$24,308",
    "FechadelPago": "20/08/2025",
    "ImportePagado": "$24,308",
    "NodeOperacion": "5332904",
    "LlavedePago": "01C967AB80",
    "Periodo": "Julio",
    "Marca": "",
    "FechadeConsulta": "26-08-2025"
  },
  {
    "Rfc": "SAM1411198N7",
    "VencimientoObligacion": "25/08/2025",
    "FechayHoradeEmision": "26/08/2025 - 10:42",
    "VigenteHasta": "25/08/2025",
    "LineadeCaptura": "0425 5JI7 9800 4705 6422",
    "ImporteTotalaPagar": "$115,324",
    "FechadelPago": "25/08/2025",
    "ImportePagado": "$115,324",
    "NodeOperacion": "122375858586",
    "LlavedePago": "AAB6E85789",
    "Periodo": "Julio",
    "Marca": "",
    "FechadeConsulta": "26-08-2025"
  },
  {
    "Rfc": "SER2205195L5",
    "VencimientoObligacion": "25/08/2025",
    "FechayHoradeEmision": "26/08/2025 - 10:42",
    "VigenteHasta": "25/08/2025",
    "LineadeCaptura": "0425 5WZ8 0700 4705 1430",
    "ImporteTotalaPagar": "$31,544",
    "FechadelPago": "25/08/2025",
    "ImportePagado": "$31,544",
    "NodeOperacion": "122375896123",
    "LlavedePago": "7676FD2581",
    "Periodo": "Julio",
    "Marca": "",
    "FechadeConsulta": "26-08-2025"
  },
  {
    "Rfc": "SER2205195L5",
    "VencimientoObligacion": "25/08/2025",
    "FechayHoradeEmision": "26/08/2025 - 10:42",
    "VigenteHasta": "25/08/2025",
    "LineadeCaptura": "0425 5FRO 1800 4705 5454",
    "ImporteTotalaPagar": "$4,915",
    "FechadelPago": "11/08/2025",
    "ImportePagado": "$4,915",
    "NodeOperacion": "122235870577",
    "LlavedePago": "F00DC5BC88",
    "Periodo": "Julio",
    "Marca": "",
    "FechadeConsulta": "26-08-2025"
  },
  {
    "Rfc": "SPA070110BI2",
    "VencimientoObligacion": "25/08/2025",
    "FechayHoradeEmision": "26/08/2025 - 10:42",
    "VigenteHasta": "25/08/2025",
    "LineadeCaptura": "0425 5PTL 8700 4705 6443",
    "ImporteTotalaPagar": "$26,402",
    "FechadelPago": "18/08/2025",
    "ImportePagado": "$26,402",
    "NodeOperacion": "50251490",
    "LlavedePago": "BA0950AD81",
    "Periodo": "Julio",
    "Marca": "",
    "FechadeConsulta": "26-08-2025"
  },
  {
    "Rfc": "SSP210810PP0",
    "VencimientoObligacion": "25/08/2025",
    "FechayHoradeEmision": "26/08/2025 - 10:43",
    "VigenteHasta": "25/08/2025",
    "LineadeCaptura": "0425 5I47 4000 4705 3467",
    "ImporteTotalaPagar": "$67,019",
    "FechadelPago": "14/08/2025",
    "ImportePagado": "$67,019",
    "NodeOperacion": "122265025108",
    "LlavedePago": "9B8D020782",
    "Periodo": "Julio",
    "Marca": "",
    "FechadeConsulta": "26-08-2025"
  },
  {
    "Rfc": "TAVF700920GZ6",
    "VencimientoObligacion": "25/08/2025",
    "FechayHoradeEmision": " 26/08/2025 - 10:4",
    "VigenteHasta": "25/08/2025",
    "LineadeCaptura": "0425 5U0I 3600 4705 9291",
    "ImporteTotalaPagar": "$35,049",
    "FechadelPago": "25/08/2025",
    "ImportePagado": "$35,049",
    "NodeOperacion": "5347944",
    "LlavedePago": "9AE756EA83",
    "Periodo": "Julio",
    "Marca": "",
    "FechadeConsulta": "26-08-2025"
  },
  {
    "Rfc": "TFU201030RNA",
    "VencimientoObligacion": "25/08/2025",
    "FechayHoradeEmision": "26/08/2025 - 10:43",
    "VigenteHasta": "25/08/2025",
    "LineadeCaptura": "0425 5IY0 7900 4705 5432",
    "ImporteTotalaPagar": "$16,516",
    "FechadelPago": "12/08/2025",
    "ImportePagado": "$16,516",
    "NodeOperacion": "50165222",
    "LlavedePago": "737C3AED80",
    "Periodo": "Julio",
    "Marca": "",
    "FechadeConsulta": "26-08-2025"
  },
  {
    "Rfc": "UMC2210198H9",
    "VencimientoObligacion": "25/08/2025",
    "FechayHoradeEmision": "26/08/2025 - 10:44",
    "VigenteHasta": "25/08/2025",
    "LineadeCaptura": "0425 5QEH 2600 4705 9416",
    "ImporteTotalaPagar": "$17,584",
    "FechadelPago": "25/08/2025",
    "ImportePagado": "$17,584",
    "NodeOperacion": "122375821918",
    "LlavedePago": "8103100C85",
    "Periodo": "Julio",
    "Marca": "",
    "FechadeConsulta": "26-08-2025"
  },
  {
    "Rfc": "VEAE570109G17",
    "VencimientoObligacion": "25/08/2025",
    "FechayHoradeEmision": " 26/08/2025 - 10:4",
    "VigenteHasta": "25/08/2025",
    "LineadeCaptura": "0425 5O10 2000 4705 6271",
    "ImporteTotalaPagar": "$97,903",
    "FechadelPago": "18/08/2025",
    "ImportePagado": "$97,903",
    "NodeOperacion": "3550257094",
    "LlavedePago": "D9275A7C89",
    "Periodo": "Julio",
    "Marca": "",
    "FechadeConsulta": "26-08-2025"
  },
  {
    "Rfc": "WCO211119QL1",
    "VencimientoObligacion": "25/08/2025",
    "FechayHoradeEmision": "26/08/2025 - 10:44",
    "VigenteHasta": "25/08/2025",
    "LineadeCaptura": "0425 5WJ9 1900 4705 1489",
    "ImporteTotalaPagar": "$20,072",
    "FechadelPago": "25/08/2025",
    "ImportePagado": "$20,072",
    "NodeOperacion": "579320223725",
    "LlavedePago": "4D1D70F181",
    "Periodo": "Julio",
    "Marca": "",
    "FechadeConsulta": "26-08-2025"
  },
  {
    "Rfc": "WCO211119QL1",
    "VencimientoObligacion": "25/08/2025",
    "FechayHoradeEmision": "26/08/2025 - 10:44",
    "VigenteHasta": "25/08/2025",
    "LineadeCaptura": "0425 5A1A 4600 4705 0481",
    "ImporteTotalaPagar": "$7,832",
    "FechadelPago": "25/08/2025",
    "ImportePagado": "$7,832",
    "NodeOperacion": "579666023725",
    "LlavedePago": "3FA24FD683",
    "Periodo": "Julio",
    "Marca": "",
    "FechadeConsulta": "26-08-2025"
  },
  {
    "Rfc": "XQR190529BA7",
    "VencimientoObligacion": "25/08/2025",
    "FechayHoradeEmision": "26/08/2025 - 10:44",
    "VigenteHasta": "25/08/2025",
    "LineadeCaptura": "0425 5VRB 5500 4705 8459",
    "ImporteTotalaPagar": "$209,612",
    "FechadelPago": "22/08/2025",
    "ImportePagado": "$209,612",
    "NodeOperacion": "50359860",
    "LlavedePago": "DFBE216B82",
    "Periodo": "Julio",
    "Marca": "",
    "FechadeConsulta": "26-08-2025"
  }
]