[
  {
    "Rfc": "RFC",
    "VencimientoObligacion": "Vencimiento Obligacion",
    "FechayHoradeEmision": "Fecha y Hora de Emision",
    "VigenteHasta": "Vigente Hasta",
    "LineadeCaptura": "Linea de Captura",
    "ImporteTotalaPagar": "Importe Total a Pagar",
    "FechadelPago": "Fecha del Pago",
    "ImportePagado": "Importe Pagado",
    "NodeOperacion": "No de Operaci\u00F3n",
    "LlavedePago": "Llave de Pago",
    "Periodo": "Periodo",
    "Marca": "Marca",
    "FechadeConsulta": "Fecha de Consulta"
  },
  {
    "Rfc": "AASC7809053S0",
    "VencimientoObligacion": "21/08/2025",
    "FechayHoradeEmision": " 21/08/2025 - 12:0",
    "VigenteHasta": "21/08/2025",
    "LineadeCaptura": "0425 5AW6 1100 4701 7202",
    "ImporteTotalaPagar": "$926",
    "FechadelPago": "18/08/2025",
    "ImportePagado": "$926",
    "NodeOperacion": "558600823025",
    "LlavedePago": "1E4780F383",
    "Periodo": "Julio",
    "Marca": "",
    "FechadeConsulta": "21-08-2025"
  },
  {
    "Rfc": "AEA100625Q60",
    "VencimientoObligacion": "21/08/2025",
    "FechayHoradeEmision": "21/08/2025 - 12:01",
    "VigenteHasta": "21/08/2025",
    "LineadeCaptura": "0425 5RTI 7900 4701 8432",
    "ImporteTotalaPagar": "$30,041",
    "FechadelPago": "19/08/2025",
    "ImportePagado": "$30,041",
    "NodeOperacion": "106199",
    "LlavedePago": "9C9D73F986",
    "Periodo": "Julio",
    "Marca": "",
    "FechadeConsulta": "21-08-2025"
  },
  {
    "Rfc": "AFR101005PY2",
    "VencimientoObligacion": "",
    "FechayHoradeEmision": "",
    "VigenteHasta": "",
    "LineadeCaptura": "",
    "ImporteTotalaPagar": "",
    "FechadelPago": "",
    "ImportePagado": "",
    "NodeOperacion": "",
    "LlavedePago": "",
    "Periodo": "Julio",
    "Marca": "No presentado",
    "FechadeConsulta": "21-08-2025"
  },
  {
    "Rfc": "AMA980706C5A",
    "VencimientoObligacion": "21/08/2025",
    "FechayHoradeEmision": "21/08/2025 - 12:01",
    "VigenteHasta": "21/08/2025",
    "LineadeCaptura": "0425 5GWX 3800 4701 7443",
    "ImporteTotalaPagar": "$31,490",
    "FechadelPago": "19/08/2025",
    "ImportePagado": "$31,490",
    "NodeOperacion": "19443007144",
    "LlavedePago": "6857A55281",
    "Periodo": "Julio",
    "Marca": "",
    "FechadeConsulta": "21-08-2025"
  },
  {
    "Rfc": "ATM221025GY2",
    "VencimientoObligacion": "18/08/2025",
    "FechayHoradeEmision": "21/08/2025 - 12:02",
    "VigenteHasta": "18/08/2025",
    "LineadeCaptura": "0425 5IF8 8000 4698 1420",
    "ImporteTotalaPagar": "$26,946",
    "FechadelPago": "13/08/2025",
    "ImportePagado": "$26,946",
    "NodeOperacion": "122255972366",
    "LlavedePago": "23F57B5B81",
    "Periodo": "Julio",
    "Marca": "",
    "FechadeConsulta": "21-08-2025"
  },
  {
    "Rfc": "AUCA031116N27",
    "VencimientoObligacion": "21/08/2025",
    "FechayHoradeEmision": " 21/08/2025 - 12:0",
    "VigenteHasta": "21/08/2025",
    "LineadeCaptura": "0425 5IDO 7500 4701 5214",
    "ImporteTotalaPagar": "$39,980",
    "FechadelPago": "14/08/2025",
    "ImportePagado": "$39,980",
    "NodeOperacion": "122265015586",
    "LlavedePago": "0202BF4B89",
    "Periodo": "Julio",
    "Marca": "",
    "FechadeConsulta": "21-08-2025"
  },
  {
    "Rfc": "BABB850316D44",
    "VencimientoObligacion": "",
    "FechayHoradeEmision": "",
    "VigenteHasta": "",
    "LineadeCaptura": "",
    "ImporteTotalaPagar": "",
    "FechadelPago": "",
    "ImportePagado": "",
    "NodeOperacion": "",
    "LlavedePago": "",
    "Periodo": "Julio",
    "Marca": "No presentado",
    "FechadeConsulta": "21-08-2025"
  },
  {
    "Rfc": "BARJ840305Q49",
    "VencimientoObligacion": "",
    "FechayHoradeEmision": "",
    "VigenteHasta": "",
    "LineadeCaptura": "",
    "ImporteTotalaPagar": "",
    "FechadelPago": "",
    "ImportePagado": "",
    "NodeOperacion": "",
    "LlavedePago": "",
    "Periodo": "Julio",
    "Marca": "No presentado",
    "FechadeConsulta": "21-08-2025"
  },
  {
    "Rfc": "BEFM8407167Y6",
    "VencimientoObligacion": "",
    "FechayHoradeEmision": "",
    "VigenteHasta": "",
    "LineadeCaptura": "",
    "ImporteTotalaPagar": "",
    "FechadelPago": "",
    "ImportePagado": "",
    "NodeOperacion": "",
    "LlavedePago": "",
    "Periodo": "Julio",
    "Marca": "No presentado",
    "FechadeConsulta": "21-08-2025"
  },
  {
    "Rfc": "CADN881016LFA",
    "VencimientoObligacion": "",
    "FechayHoradeEmision": "",
    "VigenteHasta": "",
    "LineadeCaptura": "",
    "ImporteTotalaPagar": "",
    "FechadelPago": "",
    "ImportePagado": "",
    "NodeOperacion": "",
    "LlavedePago": "",
    "Periodo": "Julio",
    "Marca": "No presentado",
    "FechadeConsulta": "21-08-2025"
  },
  {
    "Rfc": "CBA1610052X8",
    "VencimientoObligacion": "",
    "FechayHoradeEmision": "",
    "VigenteHasta": "",
    "LineadeCaptura": "",
    "ImporteTotalaPagar": "",
    "FechadelPago": "",
    "ImportePagado": "",
    "NodeOperacion": "",
    "LlavedePago": "",
    "Periodo": "Julio",
    "Marca": "No presentado",
    "FechadeConsulta": "21-08-2025"
  },
  {
    "Rfc": "CCU090116SH3",
    "VencimientoObligacion": "",
    "FechayHoradeEmision": "",
    "VigenteHasta": "",
    "LineadeCaptura": "",
    "ImporteTotalaPagar": "",
    "FechadelPago": "",
    "ImportePagado": "",
    "NodeOperacion": "",
    "LlavedePago": "",
    "Periodo": "Julio",
    "Marca": "No presentado",
    "FechadeConsulta": "21-08-2025"
  },
  {
    "Rfc": "CEM191126456",
    "VencimientoObligacion": "21/08/2025",
    "FechayHoradeEmision": "21/08/2025 - 12:03",
    "VigenteHasta": "21/08/2025",
    "LineadeCaptura": "0425 5RDO 1200 4701 2488",
    "ImporteTotalaPagar": "$24,037",
    "FechadelPago": "20/08/2025",
    "ImportePagado": "$24,037",
    "NodeOperacion": "29360",
    "LlavedePago": "CECA1D0685",
    "Periodo": "Julio",
    "Marca": "",
    "FechadeConsulta": "21-08-2025"
  },
  {
    "Rfc": "CGA050225TH4",
    "VencimientoObligacion": "",
    "FechayHoradeEmision": "",
    "VigenteHasta": "",
    "LineadeCaptura": "",
    "ImporteTotalaPagar": "",
    "FechadelPago": "",
    "ImportePagado": "",
    "NodeOperacion": "",
    "LlavedePago": "",
    "Periodo": "Julio",
    "Marca": "No presentado",
    "FechadeConsulta": "21-08-2025"
  },
  {
    "Rfc": "CIP010816D70",
    "VencimientoObligacion": "",
    "FechayHoradeEmision": "",
    "VigenteHasta": "",
    "LineadeCaptura": "",
    "ImporteTotalaPagar": "",
    "FechadelPago": "",
    "ImportePagado": "",
    "NodeOperacion": "",
    "LlavedePago": "",
    "Periodo": "Julio",
    "Marca": "No presentado",
    "FechadeConsulta": "21-08-2025"
  },
  {
    "Rfc": "CIP230705RZA",
    "VencimientoObligacion": "",
    "FechayHoradeEmision": "",
    "VigenteHasta": "",
    "LineadeCaptura": "",
    "ImporteTotalaPagar": "",
    "FechadelPago": "",
    "ImportePagado": "",
    "NodeOperacion": "",
    "LlavedePago": "",
    "Periodo": "Julio",
    "Marca": "No presentado",
    "FechadeConsulta": "21-08-2025"
  },
  {
    "Rfc": "CIV221026R66",
    "VencimientoObligacion": "",
    "FechayHoradeEmision": "",
    "VigenteHasta": "",
    "LineadeCaptura": "",
    "ImporteTotalaPagar": "",
    "FechadelPago": "",
    "ImportePagado": "",
    "NodeOperacion": "",
    "LlavedePago": "",
    "Periodo": "Julio",
    "Marca": "No presentado",
    "FechadeConsulta": "21-08-2025"
  },
  {
    "Rfc": "CNE180505P37",
    "VencimientoObligacion": "",
    "FechayHoradeEmision": "",
    "VigenteHasta": "",
    "LineadeCaptura": "",
    "ImporteTotalaPagar": "",
    "FechadelPago": "",
    "ImportePagado": "",
    "NodeOperacion": "",
    "LlavedePago": "",
    "Periodo": "Julio",
    "Marca": "No presentado",
    "FechadeConsulta": "21-08-2025"
  },
  {
    "Rfc": "COA9202061S5",
    "VencimientoObligacion": "",
    "FechayHoradeEmision": "",
    "VigenteHasta": "",
    "LineadeCaptura": "",
    "ImporteTotalaPagar": "",
    "FechadelPago": "",
    "ImportePagado": "",
    "NodeOperacion": "",
    "LlavedePago": "",
    "Periodo": "Julio",
    "Marca": "No presentado",
    "FechadeConsulta": "21-08-2025"
  },
  {
    "Rfc": "DAC010416163",
    "VencimientoObligacion": "21/08/2025",
    "FechayHoradeEmision": "21/08/2025 - 12:05",
    "VigenteHasta": "21/08/2025",
    "LineadeCaptura": "0425 5T0B 1300 4701 5466",
    "ImporteTotalaPagar": "$20,557",
    "FechadelPago": "20/08/2025",
    "ImportePagado": "$20,557",
    "NodeOperacion": "122325524600",
    "LlavedePago": "484D49D685",
    "Periodo": "Julio",
    "Marca": "",
    "FechadeConsulta": "21-08-2025"
  },
  {
    "Rfc": "DAG041126NG2",
    "VencimientoObligacion": "",
    "FechayHoradeEmision": "",
    "VigenteHasta": "",
    "LineadeCaptura": "",
    "ImporteTotalaPagar": "",
    "FechadelPago": "",
    "ImportePagado": "",
    "NodeOperacion": "",
    "LlavedePago": "",
    "Periodo": "Julio",
    "Marca": "No presentado",
    "FechadeConsulta": "21-08-2025"
  },
  {
    "Rfc": "DCJ130206RBA",
    "VencimientoObligacion": "",
    "FechayHoradeEmision": "",
    "VigenteHasta": "",
    "LineadeCaptura": "",
    "ImporteTotalaPagar": "",
    "FechadelPago": "",
    "ImportePagado": "",
    "NodeOperacion": "",
    "LlavedePago": "",
    "Periodo": "Julio",
    "Marca": "No presentado",
    "FechadeConsulta": "21-08-2025"
  },
  {
    "Rfc": "DPL210215C35",
    "VencimientoObligacion": "",
    "FechayHoradeEmision": "",
    "VigenteHasta": "",
    "LineadeCaptura": "",
    "ImporteTotalaPagar": "",
    "FechadelPago": "",
    "ImportePagado": "",
    "NodeOperacion": "",
    "LlavedePago": "",
    "Periodo": "Julio",
    "Marca": "No presentado",
    "FechadeConsulta": "21-08-2025"
  },
  {
    "Rfc": "DSI141115NM3",
    "VencimientoObligacion": "",
    "FechayHoradeEmision": "",
    "VigenteHasta": "",
    "LineadeCaptura": "",
    "ImporteTotalaPagar": "",
    "FechadelPago": "",
    "ImportePagado": "",
    "NodeOperacion": "",
    "LlavedePago": "",
    "Periodo": "Julio",
    "Marca": "No presentado",
    "FechadeConsulta": "21-08-2025"
  },
  {
    "Rfc": "DUSJ6312156E3",
    "VencimientoObligacion": "21/08/2025",
    "FechayHoradeEmision": " 21/08/2025 - 12:0",
    "VigenteHasta": "21/08/2025",
    "LineadeCaptura": "0425 5N97 8700 4701 3290",
    "ImporteTotalaPagar": "$44,913",
    "FechadelPago": "15/08/2025",
    "ImportePagado": "$44,913",
    "NodeOperacion": "9753186",
    "LlavedePago": "7B91AED784",
    "Periodo": "Julio",
    "Marca": "",
    "FechadeConsulta": "21-08-2025"
  },
  {
    "Rfc": "EAGR620526LN0",
    "VencimientoObligacion": "",
    "FechayHoradeEmision": "",
    "VigenteHasta": "",
    "LineadeCaptura": "",
    "ImporteTotalaPagar": "",
    "FechadelPago": "",
    "ImportePagado": "",
    "NodeOperacion": "",
    "LlavedePago": "",
    "Periodo": "Julio",
    "Marca": "No presentado",
    "FechadeConsulta": "21-08-2025"
  },
  {
    "Rfc": "FAL230125TB6",
    "VencimientoObligacion": "",
    "FechayHoradeEmision": "",
    "VigenteHasta": "",
    "LineadeCaptura": "",
    "ImporteTotalaPagar": "",
    "FechadelPago": "",
    "ImportePagado": "",
    "NodeOperacion": "",
    "LlavedePago": "",
    "Periodo": "Julio",
    "Marca": "No presentado",
    "FechadeConsulta": "21-08-2025"
  },
  {
    "Rfc": "FAVN611225489",
    "VencimientoObligacion": "",
    "FechayHoradeEmision": "",
    "VigenteHasta": "",
    "LineadeCaptura": "",
    "ImporteTotalaPagar": "",
    "FechadelPago": "",
    "ImportePagado": "",
    "NodeOperacion": "",
    "LlavedePago": "",
    "Periodo": "Julio",
    "Marca": "No presentado",
    "FechadeConsulta": "21-08-2025"
  },
  {
    "Rfc": "FOMY991125GE5",
    "VencimientoObligacion": "21/08/2025",
    "FechayHoradeEmision": " 21/08/2025 - 12:0",
    "VigenteHasta": "21/08/2025",
    "LineadeCaptura": "0425 5CQ4 5100 4701 7296",
    "ImporteTotalaPagar": "$6,867",
    "FechadelPago": "14/08/2025",
    "ImportePagado": "$6,867",
    "NodeOperacion": "24594",
    "LlavedePago": "CE5CDEFB89",
    "Periodo": "Julio",
    "Marca": "",
    "FechadeConsulta": "21-08-2025"
  },
  {
    "Rfc": "GAA121005TC7",
    "VencimientoObligacion": "",
    "FechayHoradeEmision": "",
    "VigenteHasta": "",
    "LineadeCaptura": "",
    "ImporteTotalaPagar": "",
    "FechadelPago": "",
    "ImportePagado": "",
    "NodeOperacion": "",
    "LlavedePago": "",
    "Periodo": "Julio",
    "Marca": "No presentado",
    "FechadeConsulta": "21-08-2025"
  },
  {
    "Rfc": "GAF100106BS4",
    "VencimientoObligacion": "21/08/2025",
    "FechayHoradeEmision": "21/08/2025 - 12:07",
    "VigenteHasta": "21/08/2025",
    "LineadeCaptura": "0425 5M3D 8300 4701 4460",
    "ImporteTotalaPagar": "$22,400",
    "FechadelPago": "15/08/2025",
    "ImportePagado": "$22,400",
    "NodeOperacion": "3546421023",
    "LlavedePago": "BDBB888D81",
    "Periodo": "Julio",
    "Marca": "",
    "FechadeConsulta": "21-08-2025"
  },
  {
    "Rfc": "GAS020805432",
    "VencimientoObligacion": "21/08/2025",
    "FechayHoradeEmision": "21/08/2025 - 12:08",
    "VigenteHasta": "21/08/2025",
    "LineadeCaptura": "0425 5QOI 9200 4701 2457",
    "ImporteTotalaPagar": "$172,804",
    "FechadelPago": "18/08/2025",
    "ImportePagado": "$172,804",
    "NodeOperacion": "562653123025",
    "LlavedePago": "AEA17E6A81",
    "Periodo": "Julio",
    "Marca": "",
    "FechadeConsulta": "21-08-2025"
  },
  {
    "Rfc": "GDP0902258M7",
    "VencimientoObligacion": "",
    "FechayHoradeEmision": "",
    "VigenteHasta": "",
    "LineadeCaptura": "",
    "ImporteTotalaPagar": "",
    "FechadelPago": "",
    "ImportePagado": "",
    "NodeOperacion": "",
    "LlavedePago": "",
    "Periodo": "Julio",
    "Marca": "No presentado",
    "FechadeConsulta": "21-08-2025"
  },
  {
    "Rfc": "GFA211126M95",
    "VencimientoObligacion": "",
    "FechayHoradeEmision": "",
    "VigenteHasta": "",
    "LineadeCaptura": "",
    "ImporteTotalaPagar": "",
    "FechadelPago": "",
    "ImportePagado": "",
    "NodeOperacion": "",
    "LlavedePago": "",
    "Periodo": "Julio",
    "Marca": "No presentado",
    "FechadeConsulta": "21-08-2025"
  },
  {
    "Rfc": "GIM030206KA1",
    "VencimientoObligacion": "",
    "FechayHoradeEmision": "",
    "VigenteHasta": "",
    "LineadeCaptura": "",
    "ImporteTotalaPagar": "",
    "FechadelPago": "",
    "ImportePagado": "",
    "NodeOperacion": "",
    "LlavedePago": "",
    "Periodo": "Julio",
    "Marca": "No presentado",
    "FechadeConsulta": "21-08-2025"
  },
  {
    "Rfc": "GMA201005D87",
    "VencimientoObligacion": "21/08/2025",
    "FechayHoradeEmision": "21/08/2025 - 12:09",
    "VigenteHasta": "21/08/2025",
    "LineadeCaptura": "0425 5KQD 8900 4701 9441",
    "ImporteTotalaPagar": "$40,476",
    "FechadelPago": "19/08/2025",
    "ImportePagado": "$40,476",
    "NodeOperacion": "5326445",
    "LlavedePago": "45D8DE7084",
    "Periodo": "Julio",
    "Marca": "",
    "FechadeConsulta": "21-08-2025"
  },
  {
    "Rfc": "GOCO8209262H5",
    "VencimientoObligacion": "",
    "FechayHoradeEmision": "",
    "VigenteHasta": "",
    "LineadeCaptura": "",
    "ImporteTotalaPagar": "",
    "FechadelPago": "",
    "ImportePagado": "",
    "NodeOperacion": "",
    "LlavedePago": "",
    "Periodo": "Julio",
    "Marca": "No presentado",
    "FechadeConsulta": "21-08-2025"
  },
  {
    "Rfc": "GUBI890115353",
    "VencimientoObligacion": "",
    "FechayHoradeEmision": "",
    "VigenteHasta": "",
    "LineadeCaptura": "",
    "ImporteTotalaPagar": "",
    "FechadelPago": "",
    "ImportePagado": "",
    "NodeOperacion": "",
    "LlavedePago": "",
    "Periodo": "Julio",
    "Marca": "No presentado",
    "FechadeConsulta": "21-08-2025"
  },
  {
    "Rfc": "GUCC430426J48",
    "VencimientoObligacion": "",
    "FechayHoradeEmision": "",
    "VigenteHasta": "",
    "LineadeCaptura": "",
    "ImporteTotalaPagar": "",
    "FechadelPago": "",
    "ImportePagado": "",
    "NodeOperacion": "",
    "LlavedePago": "",
    "Periodo": "Julio",
    "Marca": "No presentado",
    "FechadeConsulta": "21-08-2025"
  },
  {
    "Rfc": "GUSM5405256Z7",
    "VencimientoObligacion": "",
    "FechayHoradeEmision": "",
    "VigenteHasta": "",
    "LineadeCaptura": "",
    "ImporteTotalaPagar": "",
    "FechadelPago": "",
    "ImportePagado": "",
    "NodeOperacion": "",
    "LlavedePago": "",
    "Periodo": "Julio",
    "Marca": "No presentado",
    "FechadeConsulta": "21-08-2025"
  },
  {
    "Rfc": "HIVE710425NX8",
    "VencimientoObligacion": "",
    "FechayHoradeEmision": "",
    "VigenteHasta": "",
    "LineadeCaptura": "",
    "ImporteTotalaPagar": "",
    "FechadelPago": "",
    "ImportePagado": "",
    "NodeOperacion": "",
    "LlavedePago": "",
    "Periodo": "Julio",
    "Marca": "No presentado",
    "FechadeConsulta": "21-08-2025"
  },
  {
    "Rfc": "HLO2107065Z8",
    "VencimientoObligacion": "",
    "FechayHoradeEmision": "",
    "VigenteHasta": "",
    "LineadeCaptura": "",
    "ImporteTotalaPagar": "",
    "FechadelPago": "",
    "ImportePagado": "",
    "NodeOperacion": "",
    "LlavedePago": "",
    "Periodo": "Julio",
    "Marca": "No presentado",
    "FechadeConsulta": "21-08-2025"
  },
  {
    "Rfc": "LIMA760325JS6",
    "VencimientoObligacion": "",
    "FechayHoradeEmision": "",
    "VigenteHasta": "",
    "LineadeCaptura": "",
    "ImporteTotalaPagar": "",
    "FechadelPago": "",
    "ImportePagado": "",
    "NodeOperacion": "",
    "LlavedePago": "",
    "Periodo": "Julio",
    "Marca": "No presentado",
    "FechadeConsulta": "21-08-2025"
  },
  {
    "Rfc": "LOAF760425GD6",
    "VencimientoObligacion": "",
    "FechayHoradeEmision": "",
    "VigenteHasta": "",
    "LineadeCaptura": "",
    "ImporteTotalaPagar": "",
    "FechadelPago": "",
    "ImportePagado": "",
    "NodeOperacion": "",
    "LlavedePago": "",
    "Periodo": "Julio",
    "Marca": "No presentado",
    "FechadeConsulta": "21-08-2025"
  },
  {
    "Rfc": "LOBJ661005B42",
    "VencimientoObligacion": "",
    "FechayHoradeEmision": "",
    "VigenteHasta": "",
    "LineadeCaptura": "",
    "ImporteTotalaPagar": "",
    "FechadelPago": "",
    "ImportePagado": "",
    "NodeOperacion": "",
    "LlavedePago": "",
    "Periodo": "Julio",
    "Marca": "No presentado",
    "FechadeConsulta": "21-08-2025"
  },
  {
    "Rfc": "LOLA730726MU4",
    "VencimientoObligacion": "",
    "FechayHoradeEmision": "",
    "VigenteHasta": "",
    "LineadeCaptura": "",
    "ImporteTotalaPagar": "",
    "FechadelPago": "",
    "ImportePagado": "",
    "NodeOperacion": "",
    "LlavedePago": "",
    "Periodo": "Julio",
    "Marca": "No presentado",
    "FechadeConsulta": "21-08-2025"
  },
  {
    "Rfc": "LOLJ861215318",
    "VencimientoObligacion": "",
    "FechayHoradeEmision": "",
    "VigenteHasta": "",
    "LineadeCaptura": "",
    "ImporteTotalaPagar": "",
    "FechadelPago": "",
    "ImportePagado": "",
    "NodeOperacion": "",
    "LlavedePago": "",
    "Periodo": "Julio",
    "Marca": "No presentado",
    "FechadeConsulta": "21-08-2025"
  },
  {
    "Rfc": "LOPG6801156H1",
    "VencimientoObligacion": "",
    "FechayHoradeEmision": "",
    "VigenteHasta": "",
    "LineadeCaptura": "",
    "ImporteTotalaPagar": "",
    "FechadelPago": "",
    "ImportePagado": "",
    "NodeOperacion": "",
    "LlavedePago": "",
    "Periodo": "Julio",
    "Marca": "No presentado",
    "FechadeConsulta": "21-08-2025"
  },
  {
    "Rfc": "LTL1310258AA",
    "VencimientoObligacion": "21/08/2025",
    "FechayHoradeEmision": "21/08/2025 - 12:11",
    "VigenteHasta": "21/08/2025",
    "LineadeCaptura": "0425 5MQV 6400 4701 7457",
    "ImporteTotalaPagar": "$52,587",
    "FechadelPago": "20/08/2025",
    "ImportePagado": "$52,587",
    "NodeOperacion": "122325501035",
    "LlavedePago": "4891E52181",
    "Periodo": "Julio",
    "Marca": "",
    "FechadeConsulta": "21-08-2025"
  },
  {
    "Rfc": "MAGC8708064C8",
    "VencimientoObligacion": "",
    "FechayHoradeEmision": "",
    "VigenteHasta": "",
    "LineadeCaptura": "",
    "ImporteTotalaPagar": "",
    "FechadelPago": "",
    "ImportePagado": "",
    "NodeOperacion": "",
    "LlavedePago": "",
    "Periodo": "Julio",
    "Marca": "No presentado",
    "FechadeConsulta": "21-08-2025"
  },
  {
    "Rfc": "MALD050705GR6",
    "VencimientoObligacion": "",
    "FechayHoradeEmision": "",
    "VigenteHasta": "",
    "LineadeCaptura": "",
    "ImporteTotalaPagar": "",
    "FechadelPago": "",
    "ImportePagado": "",
    "NodeOperacion": "",
    "LlavedePago": "",
    "Periodo": "Julio",
    "Marca": "No presentado",
    "FechadeConsulta": "21-08-2025"
  },
  {
    "Rfc": "MAMA5902154G0",
    "VencimientoObligacion": "",
    "FechayHoradeEmision": "",
    "VigenteHasta": "",
    "LineadeCaptura": "",
    "ImporteTotalaPagar": "",
    "FechadelPago": "",
    "ImportePagado": "",
    "NodeOperacion": "",
    "LlavedePago": "",
    "Periodo": "Julio",
    "Marca": "No presentado",
    "FechadeConsulta": "21-08-2025"
  },
  {
    "Rfc": "MAP160126BL0",
    "VencimientoObligacion": "",
    "FechayHoradeEmision": "",
    "VigenteHasta": "",
    "LineadeCaptura": "",
    "ImporteTotalaPagar": "",
    "FechadelPago": "",
    "ImportePagado": "",
    "NodeOperacion": "",
    "LlavedePago": "",
    "Periodo": "Julio",
    "Marca": "No presentado",
    "FechadeConsulta": "21-08-2025"
  },
  {
    "Rfc": "MASA740315CSA",
    "VencimientoObligacion": "",
    "FechayHoradeEmision": "",
    "VigenteHasta": "",
    "LineadeCaptura": "",
    "ImporteTotalaPagar": "",
    "FechadelPago": "",
    "ImportePagado": "",
    "NodeOperacion": "",
    "LlavedePago": "",
    "Periodo": "Julio",
    "Marca": "No presentado",
    "FechadeConsulta": "21-08-2025"
  },
  {
    "Rfc": "MCA141105IQ7",
    "VencimientoObligacion": "",
    "FechayHoradeEmision": "",
    "VigenteHasta": "",
    "LineadeCaptura": "",
    "ImporteTotalaPagar": "",
    "FechadelPago": "",
    "ImportePagado": "",
    "NodeOperacion": "",
    "LlavedePago": "",
    "Periodo": "Julio",
    "Marca": "No presentado",
    "FechadeConsulta": "21-08-2025"
  },
  {
    "Rfc": "MCA1703154F6",
    "VencimientoObligacion": "",
    "FechayHoradeEmision": "",
    "VigenteHasta": "",
    "LineadeCaptura": "",
    "ImporteTotalaPagar": "",
    "FechadelPago": "",
    "ImportePagado": "",
    "NodeOperacion": "",
    "LlavedePago": "",
    "Periodo": "Julio",
    "Marca": "No presentado",
    "FechadeConsulta": "21-08-2025"
  },
  {
    "Rfc": "MCR890406691",
    "VencimientoObligacion": "21/08/2025",
    "FechayHoradeEmision": "21/08/2025 - 12:13",
    "VigenteHasta": "21/08/2025",
    "LineadeCaptura": "0425 5HFS 2500 4701 9427",
    "ImporteTotalaPagar": "$28,777",
    "FechadelPago": "20/08/2025",
    "ImportePagado": "$28,777",
    "NodeOperacion": "11945784",
    "LlavedePago": "AFB8979C80",
    "Periodo": "Julio",
    "Marca": "",
    "FechadeConsulta": "21-08-2025"
  },
  {
    "Rfc": "MME170925PX8",
    "VencimientoObligacion": "",
    "FechayHoradeEmision": "",
    "VigenteHasta": "",
    "LineadeCaptura": "",
    "ImporteTotalaPagar": "",
    "FechadelPago": "",
    "ImportePagado": "",
    "NodeOperacion": "",
    "LlavedePago": "",
    "Periodo": "Julio",
    "Marca": "No presentado",
    "FechadeConsulta": "21-08-2025"
  },
  {
    "Rfc": "MORE6206056C8",
    "VencimientoObligacion": "21/08/2025",
    "FechayHoradeEmision": " 21/08/2025 - 12:1",
    "VigenteHasta": "21/08/2025",
    "LineadeCaptura": "0425 5RG6 1600 4701 7286",
    "ImporteTotalaPagar": "$744",
    "FechadelPago": "19/08/2025",
    "ImportePagado": "$744",
    "NodeOperacion": "122315382584",
    "LlavedePago": "5E36490981",
    "Periodo": "Julio",
    "Marca": "",
    "FechadeConsulta": "21-08-2025"
  },
  {
    "Rfc": "MORL911205I87",
    "VencimientoObligacion": "21/08/2025",
    "FechayHoradeEmision": " 21/08/2025 - 12:1",
    "VigenteHasta": "21/08/2025",
    "LineadeCaptura": "0425 5ROC 2800 4701 0283",
    "ImporteTotalaPagar": "$11,130",
    "FechadelPago": "20/08/2025",
    "ImportePagado": "$11,130",
    "NodeOperacion": "50317275",
    "LlavedePago": "086854A982",
    "Periodo": "Julio",
    "Marca": "",
    "FechadeConsulta": "21-08-2025"
  },
  {
    "Rfc": "MPA200616I59",
    "VencimientoObligacion": "",
    "FechayHoradeEmision": "",
    "VigenteHasta": "",
    "LineadeCaptura": "",
    "ImporteTotalaPagar": "",
    "FechadelPago": "",
    "ImportePagado": "",
    "NodeOperacion": "",
    "LlavedePago": "",
    "Periodo": "Julio",
    "Marca": "No presentado",
    "FechadeConsulta": "21-08-2025"
  },
  {
    "Rfc": "MTE2305051T5",
    "VencimientoObligacion": "",
    "FechayHoradeEmision": "",
    "VigenteHasta": "",
    "LineadeCaptura": "",
    "ImporteTotalaPagar": "",
    "FechadelPago": "",
    "ImportePagado": "",
    "NodeOperacion": "",
    "LlavedePago": "",
    "Periodo": "Julio",
    "Marca": "No presentado",
    "FechadeConsulta": "21-08-2025"
  },
  {
    "Rfc": "MURV630205HZA",
    "VencimientoObligacion": "21/08/2025",
    "FechayHoradeEmision": " 21/08/2025 - 12:1",
    "VigenteHasta": "21/08/2025",
    "LineadeCaptura": "0425 5SEE 7900 4701 9219",
    "ImporteTotalaPagar": "$29,293",
    "FechadelPago": "19/08/2025",
    "ImportePagado": "$29,293",
    "NodeOperacion": "567963123125",
    "LlavedePago": "87EA323E81",
    "Periodo": "Julio",
    "Marca": "",
    "FechadeConsulta": "21-08-2025"
  },
  {
    "Rfc": "MURV630205HZA",
    "VencimientoObligacion": "21/08/2025",
    "FechayHoradeEmision": " 21/08/2025 - 12:1",
    "VigenteHasta": "21/08/2025",
    "LineadeCaptura": "0425 5RV2 9600 4701 4238",
    "ImporteTotalaPagar": "$12,937",
    "FechadelPago": "19/08/2025",
    "ImportePagado": "$12,937",
    "NodeOperacion": "566679723125",
    "LlavedePago": "183AD90988",
    "Periodo": "Julio",
    "Marca": "",
    "FechadeConsulta": "21-08-2025"
  },
  {
    "Rfc": "MUSM920325EL4",
    "VencimientoObligacion": "",
    "FechayHoradeEmision": "",
    "VigenteHasta": "",
    "LineadeCaptura": "",
    "ImporteTotalaPagar": "",
    "FechadelPago": "",
    "ImportePagado": "",
    "NodeOperacion": "",
    "LlavedePago": "",
    "Periodo": "Julio",
    "Marca": "No presentado",
    "FechadeConsulta": "21-08-2025"
  },
  {
    "Rfc": "OMS100305LX5",
    "VencimientoObligacion": "",
    "FechayHoradeEmision": "",
    "VigenteHasta": "",
    "LineadeCaptura": "",
    "ImporteTotalaPagar": "",
    "FechadelPago": "",
    "ImportePagado": "",
    "NodeOperacion": "",
    "LlavedePago": "",
    "Periodo": "Julio",
    "Marca": "No presentado",
    "FechadeConsulta": "21-08-2025"
  },
  {
    "Rfc": "ONC161125493",
    "VencimientoObligacion": "",
    "FechayHoradeEmision": "",
    "VigenteHasta": "",
    "LineadeCaptura": "",
    "ImporteTotalaPagar": "",
    "FechadelPago": "",
    "ImportePagado": "",
    "NodeOperacion": "",
    "LlavedePago": "",
    "Periodo": "Julio",
    "Marca": "No presentado",
    "FechadeConsulta": "21-08-2025"
  },
  {
    "Rfc": "PAFR420826UA5",
    "VencimientoObligacion": "21/08/2025",
    "FechayHoradeEmision": " 21/08/2025 - 12:1",
    "VigenteHasta": "21/08/2025",
    "LineadeCaptura": "0425 5LHA 6000 4701 1292",
    "ImporteTotalaPagar": "$14,992",
    "FechadelPago": "20/08/2025",
    "ImportePagado": "$14,992",
    "NodeOperacion": "371251523225",
    "LlavedePago": "77F9142581",
    "Periodo": "Julio",
    "Marca": "",
    "FechadeConsulta": "21-08-2025"
  },
  {
    "Rfc": "PEBR640406QV2",
    "VencimientoObligacion": "18/08/2025",
    "FechayHoradeEmision": " 21/08/2025 - 12:1",
    "VigenteHasta": "18/08/2025",
    "LineadeCaptura": "0425 5QJM 1300 4698 4221",
    "ImporteTotalaPagar": "$10,326",
    "FechadelPago": "18/08/2025",
    "ImportePagado": "$10,326",
    "NodeOperacion": "5323278",
    "LlavedePago": "0D7C7EB084",
    "Periodo": "Julio",
    "Marca": "",
    "FechadeConsulta": "21-08-2025"
  },
  {
    "Rfc": "PILM790225723",
    "VencimientoObligacion": "",
    "FechayHoradeEmision": "",
    "VigenteHasta": "",
    "LineadeCaptura": "",
    "ImporteTotalaPagar": "",
    "FechadelPago": "",
    "ImportePagado": "",
    "NodeOperacion": "",
    "LlavedePago": "",
    "Periodo": "Julio",
    "Marca": "No presentado",
    "FechadeConsulta": "21-08-2025"
  },
  {
    "Rfc": "POEF620615EB7",
    "VencimientoObligacion": "",
    "FechayHoradeEmision": "",
    "VigenteHasta": "",
    "LineadeCaptura": "",
    "ImporteTotalaPagar": "",
    "FechadelPago": "",
    "ImportePagado": "",
    "NodeOperacion": "",
    "LlavedePago": "",
    "Periodo": "Julio",
    "Marca": "No presentado",
    "FechadeConsulta": "21-08-2025"
  },
  {
    "Rfc": "POV200715DY2",
    "VencimientoObligacion": "",
    "FechayHoradeEmision": "",
    "VigenteHasta": "",
    "LineadeCaptura": "",
    "ImporteTotalaPagar": "",
    "FechadelPago": "",
    "ImportePagado": "",
    "NodeOperacion": "",
    "LlavedePago": "",
    "Periodo": "Julio",
    "Marca": "No presentado",
    "FechadeConsulta": "21-08-2025"
  },
  {
    "Rfc": "PRA930416AG9",
    "VencimientoObligacion": "",
    "FechayHoradeEmision": "",
    "VigenteHasta": "",
    "LineadeCaptura": "",
    "ImporteTotalaPagar": "",
    "FechadelPago": "",
    "ImportePagado": "",
    "NodeOperacion": "",
    "LlavedePago": "",
    "Periodo": "Julio",
    "Marca": "No presentado",
    "FechadeConsulta": "21-08-2025"
  },
  {
    "Rfc": "PRC191016R75",
    "VencimientoObligacion": "",
    "FechayHoradeEmision": "",
    "VigenteHasta": "",
    "LineadeCaptura": "",
    "ImporteTotalaPagar": "",
    "FechadelPago": "",
    "ImportePagado": "",
    "NodeOperacion": "",
    "LlavedePago": "",
    "Periodo": "Julio",
    "Marca": "No presentado",
    "FechadeConsulta": "21-08-2025"
  },
  {
    "Rfc": "QUAA000915KH5",
    "VencimientoObligacion": "",
    "FechayHoradeEmision": "",
    "VigenteHasta": "",
    "LineadeCaptura": "",
    "ImporteTotalaPagar": "",
    "FechadelPago": "",
    "ImportePagado": "",
    "NodeOperacion": "",
    "LlavedePago": "",
    "Periodo": "Julio",
    "Marca": "No presentado",
    "FechadeConsulta": "21-08-2025"
  },
  {
    "Rfc": "RAJ980825FW1",
    "VencimientoObligacion": "",
    "FechayHoradeEmision": "",
    "VigenteHasta": "",
    "LineadeCaptura": "",
    "ImporteTotalaPagar": "",
    "FechadelPago": "",
    "ImportePagado": "",
    "NodeOperacion": "",
    "LlavedePago": "",
    "Periodo": "Julio",
    "Marca": "No presentado",
    "FechadeConsulta": "21-08-2025"
  },
  {
    "Rfc": "RALJ850705GX4",
    "VencimientoObligacion": "21/08/2025",
    "FechayHoradeEmision": " 21/08/2025 - 12:1",
    "VigenteHasta": "21/08/2025",
    "LineadeCaptura": "0425 5T4Y 8100 4701 2240",
    "ImporteTotalaPagar": "$5,034",
    "FechadelPago": "20/08/2025",
    "ImportePagado": "$5,034",
    "NodeOperacion": "122325592729",
    "LlavedePago": "2B49A8CE85",
    "Periodo": "Julio",
    "Marca": "",
    "FechadeConsulta": "21-08-2025"
  },
  {
    "Rfc": "RAN030606JK4",
    "VencimientoObligacion": "",
    "FechayHoradeEmision": "",
    "VigenteHasta": "",
    "LineadeCaptura": "",
    "ImporteTotalaPagar": "",
    "FechadelPago": "",
    "ImportePagado": "",
    "NodeOperacion": "",
    "LlavedePago": "",
    "Periodo": "Julio",
    "Marca": "No presentado",
    "FechadeConsulta": "21-08-2025"
  },
  {
    "Rfc": "RAS190305LD5",
    "VencimientoObligacion": "",
    "FechayHoradeEmision": "",
    "VigenteHasta": "",
    "LineadeCaptura": "",
    "ImporteTotalaPagar": "",
    "FechadelPago": "",
    "ImportePagado": "",
    "NodeOperacion": "",
    "LlavedePago": "",
    "Periodo": "Julio",
    "Marca": "No presentado",
    "FechadeConsulta": "21-08-2025"
  },
  {
    "Rfc": "RIBV760725T55",
    "VencimientoObligacion": "",
    "FechayHoradeEmision": "",
    "VigenteHasta": "",
    "LineadeCaptura": "",
    "ImporteTotalaPagar": "",
    "FechadelPago": "",
    "ImportePagado": "",
    "NodeOperacion": "",
    "LlavedePago": "",
    "Periodo": "Julio",
    "Marca": "No presentado",
    "FechadeConsulta": "21-08-2025"
  },
  {
    "Rfc": "ROMS9010062H5",
    "VencimientoObligacion": "",
    "FechayHoradeEmision": "",
    "VigenteHasta": "",
    "LineadeCaptura": "",
    "ImporteTotalaPagar": "",
    "FechadelPago": "",
    "ImportePagado": "",
    "NodeOperacion": "",
    "LlavedePago": "",
    "Periodo": "Julio",
    "Marca": "No presentado",
    "FechadeConsulta": "21-08-2025"
  },
  {
    "Rfc": "RORJ711005C37",
    "VencimientoObligacion": "",
    "FechayHoradeEmision": "",
    "VigenteHasta": "",
    "LineadeCaptura": "",
    "ImporteTotalaPagar": "",
    "FechadelPago": "",
    "ImportePagado": "",
    "NodeOperacion": "",
    "LlavedePago": "",
    "Periodo": "Julio",
    "Marca": "No presentado",
    "FechadeConsulta": "21-08-2025"
  },
  {
    "Rfc": "RUMS030516D82",
    "VencimientoObligacion": "",
    "FechayHoradeEmision": "",
    "VigenteHasta": "",
    "LineadeCaptura": "",
    "ImporteTotalaPagar": "",
    "FechadelPago": "",
    "ImportePagado": "",
    "NodeOperacion": "",
    "LlavedePago": "",
    "Periodo": "Julio",
    "Marca": "No presentado",
    "FechadeConsulta": "21-08-2025"
  },
  {
    "Rfc": "SAG191126AD4",
    "VencimientoObligacion": "",
    "FechayHoradeEmision": "",
    "VigenteHasta": "",
    "LineadeCaptura": "",
    "ImporteTotalaPagar": "",
    "FechadelPago": "",
    "ImportePagado": "",
    "NodeOperacion": "",
    "LlavedePago": "",
    "Periodo": "Julio",
    "Marca": "No presentado",
    "FechadeConsulta": "21-08-2025"
  },
  {
    "Rfc": "SAL170816N98",
    "VencimientoObligacion": "21/08/2025",
    "FechayHoradeEmision": "21/08/2025 - 12:19",
    "VigenteHasta": "21/08/2025",
    "LineadeCaptura": "0425 5Q6T 5500 4701 2412",
    "ImporteTotalaPagar": "$37,819",
    "FechadelPago": "18/08/2025",
    "ImportePagado": "$37,819",
    "NodeOperacion": "122305306671",
    "LlavedePago": "6FBF331086",
    "Periodo": "Julio",
    "Marca": "",
    "FechadeConsulta": "21-08-2025"
  },
  {
    "Rfc": "SAZM0004253U5",
    "VencimientoObligacion": "",
    "FechayHoradeEmision": "",
    "VigenteHasta": "",
    "LineadeCaptura": "",
    "ImporteTotalaPagar": "",
    "FechadelPago": "",
    "ImportePagado": "",
    "NodeOperacion": "",
    "LlavedePago": "",
    "Periodo": "Julio",
    "Marca": "No presentado",
    "FechadeConsulta": "21-08-2025"
  },
  {
    "Rfc": "SCT190206881",
    "VencimientoObligacion": "",
    "FechayHoradeEmision": "",
    "VigenteHasta": "",
    "LineadeCaptura": "",
    "ImporteTotalaPagar": "",
    "FechadelPago": "",
    "ImportePagado": "",
    "NodeOperacion": "",
    "LlavedePago": "",
    "Periodo": "Julio",
    "Marca": "No presentado",
    "FechadeConsulta": "21-08-2025"
  },
  {
    "Rfc": "SEE1909251U0",
    "VencimientoObligacion": "21/08/2025",
    "FechayHoradeEmision": "21/08/2025 - 12:20",
    "VigenteHasta": "21/08/2025",
    "LineadeCaptura": "0425 5MGE 7500 4701 5406",
    "ImporteTotalaPagar": "$16",
    "FechadelPago": "15/08/2025",
    "ImportePagado": "$16",
    "NodeOperacion": "34644",
    "LlavedePago": "E76B845986",
    "Periodo": "Julio",
    "Marca": "",
    "FechadeConsulta": "21-08-2025"
  },
  {
    "Rfc": "SEE1909251U0",
    "VencimientoObligacion": "21/08/2025",
    "FechayHoradeEmision": "21/08/2025 - 12:20",
    "VigenteHasta": "21/08/2025",
    "LineadeCaptura": "0425 5BHX 6700 4701 2436",
    "ImporteTotalaPagar": "$1,544",
    "FechadelPago": "05/08/2025",
    "ImportePagado": "$1,544",
    "NodeOperacion": "56566",
    "LlavedePago": "B65D476B81",
    "Periodo": "Julio",
    "Marca": "",
    "FechadeConsulta": "21-08-2025"
  },
  {
    "Rfc": "SEM220405QU6",
    "VencimientoObligacion": "21/08/2025",
    "FechayHoradeEmision": "21/08/2025 - 12:20",
    "VigenteHasta": "21/08/2025",
    "LineadeCaptura": "0425 5IR3 2700 4701 5418",
    "ImporteTotalaPagar": "$55,458",
    "FechadelPago": "19/08/2025",
    "ImportePagado": "$55,458",
    "NodeOperacion": "564010723125",
    "LlavedePago": "00ABD12B84",
    "Periodo": "Julio",
    "Marca": "",
    "FechadeConsulta": "21-08-2025"
  },
  {
    "Rfc": "SIR200205HG1",
    "VencimientoObligacion": "21/08/2025",
    "FechayHoradeEmision": "21/08/2025 - 12:21",
    "VigenteHasta": "21/08/2025",
    "LineadeCaptura": "0425 5HKX 6300 4701 5439",
    "ImporteTotalaPagar": "$3,370",
    "FechadelPago": "12/08/2025",
    "ImportePagado": "$3,370",
    "NodeOperacion": "50158944",
    "LlavedePago": "CCA324CD85",
    "Periodo": "Julio",
    "Marca": "",
    "FechadeConsulta": "21-08-2025"
  },
  {
    "Rfc": "SIT211025UG3",
    "VencimientoObligacion": "",
    "FechayHoradeEmision": "",
    "VigenteHasta": "",
    "LineadeCaptura": "",
    "ImporteTotalaPagar": "",
    "FechadelPago": "",
    "ImportePagado": "",
    "NodeOperacion": "",
    "LlavedePago": "",
    "Periodo": "Julio",
    "Marca": "No presentado",
    "FechadeConsulta": "21-08-2025"
  },
  {
    "Rfc": "SOA0601163L4",
    "VencimientoObligacion": "21/08/2025",
    "FechayHoradeEmision": "21/08/2025 - 12:21",
    "VigenteHasta": "21/08/2025",
    "LineadeCaptura": "0425 5GEZ 7600 4701 1406",
    "ImporteTotalaPagar": "$24,175",
    "FechadelPago": "11/08/2025",
    "ImportePagado": "$24,175",
    "NodeOperacion": "24434074849",
    "LlavedePago": "09CECE9986",
    "Periodo": "Julio",
    "Marca": "",
    "FechadeConsulta": "21-08-2025"
  },
  {
    "Rfc": "SRR160516NL6",
    "VencimientoObligacion": "",
    "FechayHoradeEmision": "",
    "VigenteHasta": "",
    "LineadeCaptura": "",
    "ImporteTotalaPagar": "",
    "FechadelPago": "",
    "ImportePagado": "",
    "NodeOperacion": "",
    "LlavedePago": "",
    "Periodo": "Julio",
    "Marca": "No presentado",
    "FechadeConsulta": "21-08-2025"
  },
  {
    "Rfc": "SSE211125V34",
    "VencimientoObligacion": "",
    "FechayHoradeEmision": "",
    "VigenteHasta": "",
    "LineadeCaptura": "",
    "ImporteTotalaPagar": "",
    "FechadelPago": "",
    "ImportePagado": "",
    "NodeOperacion": "",
    "LlavedePago": "",
    "Periodo": "Julio",
    "Marca": "No presentado",
    "FechadeConsulta": "21-08-2025"
  },
  {
    "Rfc": "SSH070315R22",
    "VencimientoObligacion": "",
    "FechayHoradeEmision": "",
    "VigenteHasta": "",
    "LineadeCaptura": "",
    "ImporteTotalaPagar": "",
    "FechadelPago": "",
    "ImportePagado": "",
    "NodeOperacion": "",
    "LlavedePago": "",
    "Periodo": "Julio",
    "Marca": "No presentado",
    "FechadeConsulta": "21-08-2025"
  },
  {
    "Rfc": "TOSD890815237",
    "VencimientoObligacion": "21/08/2025",
    "FechayHoradeEmision": " 21/08/2025 - 12:2",
    "VigenteHasta": "21/08/2025",
    "LineadeCaptura": "0425 5RFA 0400 4701 7276",
    "ImporteTotalaPagar": "$27,200",
    "FechadelPago": "19/08/2025",
    "ImportePagado": "$27,200",
    "NodeOperacion": "565620423125",
    "LlavedePago": "B554B70B81",
    "Periodo": "Julio",
    "Marca": "",
    "FechadeConsulta": "21-08-2025"
  },
  {
    "Rfc": "TRI071206FJ7",
    "VencimientoObligacion": "21/08/2025",
    "FechayHoradeEmision": "21/08/2025 - 12:22",
    "VigenteHasta": "21/08/2025",
    "LineadeCaptura": "0425 5G0J 1400 4701 4461",
    "ImporteTotalaPagar": "$25,418",
    "FechadelPago": "09/08/2025",
    "ImportePagado": "$25,418",
    "NodeOperacion": "122215824745",
    "LlavedePago": "DA33E31C87",
    "Periodo": "Julio",
    "Marca": "",
    "FechadeConsulta": "21-08-2025"
  },
  {
    "Rfc": "VAGI591206LPA",
    "VencimientoObligacion": "",
    "FechayHoradeEmision": "",
    "VigenteHasta": "",
    "LineadeCaptura": "",
    "ImporteTotalaPagar": "",
    "FechadelPago": "",
    "ImportePagado": "",
    "NodeOperacion": "",
    "LlavedePago": "",
    "Periodo": "Julio",
    "Marca": "No presentado",
    "FechadeConsulta": "21-08-2025"
  },
  {
    "Rfc": "VARA750906JG7",
    "VencimientoObligacion": "",
    "FechayHoradeEmision": "",
    "VigenteHasta": "",
    "LineadeCaptura": "",
    "ImporteTotalaPagar": "",
    "FechadelPago": "",
    "ImportePagado": "",
    "NodeOperacion": "",
    "LlavedePago": "",
    "Periodo": "Julio",
    "Marca": "No presentado",
    "FechadeConsulta": "21-08-2025"
  },
  {
    "Rfc": "VIOR7905262G6",
    "VencimientoObligacion": "21/08/2025",
    "FechayHoradeEmision": " 21/08/2025 - 12:2",
    "VigenteHasta": "21/08/2025",
    "LineadeCaptura": "0425 5R3V 6300 4701 8280",
    "ImporteTotalaPagar": "$13,002",
    "FechadelPago": "19/08/2025",
    "ImportePagado": "$13,002",
    "NodeOperacion": "3552211863",
    "LlavedePago": "0877A9FE81",
    "Periodo": "Julio",
    "Marca": "",
    "FechadeConsulta": "21-08-2025"
  },
  {
    "Rfc": "WTF2108066M1",
    "VencimientoObligacion": "",
    "FechayHoradeEmision": "",
    "VigenteHasta": "",
    "LineadeCaptura": "",
    "ImporteTotalaPagar": "",
    "FechadelPago": "",
    "ImportePagado": "",
    "NodeOperacion": "",
    "LlavedePago": "",
    "Periodo": "Julio",
    "Marca": "No presentado",
    "FechadeConsulta": "21-08-2025"
  }
]